[
  {
    "3pa": 214,
    "3pm": 73,
    "abbr": "BOS",
    "ast": 94,
    "blk": 30,
    "fga": 508,
    "fgm": 207,
    "fpts": "1035.84",
    "fta": 131,
    "ftm": 106,
    "gp": 29,
    "min": 1392,
    "pace": 595.5,
    "pts": 594,
    "reb": 175,
    "stl": 45,
    "team": "Boston Celtics",
    "to": 62,
    "usg": "18.93"
  },
  {
    "3pa": 220,
    "3pm": 81,
    "abbr": "BKN",
    "ast": 132,
    "blk": 14,
    "fga": 567,
    "fgm": 240,
    "fpts": "1147.75",
    "fta": 134,
    "ftm": 107,
    "gp": 28,
    "min": 1344,
    "pace": 674,
    "pts": 669,
    "reb": 175,
    "stl": 57,
    "team": "Brooklyn Nets",
    "to": 75,
    "usg": "22.16"
  },
  {
    "3pa": 223,
    "3pm": 88,
    "abbr": "NYK",
    "ast": 115,
    "blk": 7,
    "fga": 544,
    "fgm": 240,
    "fpts": "1151.16",
    "fta": 152,
    "ftm": 133,
    "gp": 29,
    "min": 1392,
    "pace": 649,
    "pts": 704,
    "reb": 190,
    "stl": 47,
    "team": "New York Knicks",
    "to": 62,
    "usg": "20.43"
  },
  {
    "3pa": 203,
    "3pm": 68,
    "abbr": "PHI",
    "ast": 105,
    "blk": 17,
    "fga": 550,
    "fgm": 237,
    "fpts": "1080.30",
    "fta": 133,
    "ftm": 108,
    "gp": 28,
    "min": 1344,
    "pace": 667.5,
    "pts": 651,
    "reb": 168,
    "stl": 54,
    "team": "Philadelphia 76ers",
    "to": 75,
    "usg": "21.37"
  },
  {
    "3pa": 186,
    "3pm": 63,
    "abbr": "TOR",
    "ast": 118,
    "blk": 17,
    "fga": 426,
    "fgm": 178,
    "fpts": "870.31",
    "fta": 94,
    "ftm": 76,
    "gp": 27,
    "min": 1296,
    "pace": 521,
    "pts": 498,
    "reb": 130,
    "stl": 39,
    "team": "Toronto Raptors",
    "to": 75,
    "usg": "17.94"
  },
  {
    "3pa": 192,
    "3pm": 75,
    "abbr": "CHI",
    "ast": 142,
    "blk": 16,
    "fga": 504,
    "fgm": 227,
    "fpts": "1081.63",
    "fta": 95,
    "ftm": 72,
    "gp": 28,
    "min": 1344,
    "pace": 575.5,
    "pts": 602,
    "reb": 175,
    "stl": 39,
    "team": "Chicago Bulls",
    "to": 57,
    "usg": "19.34"
  },
  {
    "3pa": 206,
    "3pm": 79,
    "abbr": "CLE",
    "ast": 130,
    "blk": 21,
    "fga": 489,
    "fgm": 216,
    "fpts": "1070.61",
    "fta": 120,
    "ftm": 93,
    "gp": 27,
    "min": 1296,
    "pace": 578,
    "pts": 605,
    "reb": 159,
    "stl": 46,
    "team": "Cleveland Cavaliers",
    "to": 59,
    "usg": "19.87"
  },
  {
    "3pa": 196,
    "3pm": 56,
    "abbr": "DET",
    "ast": 130,
    "blk": 14,
    "fga": 518,
    "fgm": 219,
    "fpts": "1029.26",
    "fta": 136,
    "ftm": 114,
    "gp": 29,
    "min": 1392,
    "pace": 630,
    "pts": 608,
    "reb": 146,
    "stl": 42,
    "team": "Detroit Pistons",
    "to": 62,
    "usg": "19.62"
  },
  {
    "3pa": 258,
    "3pm": 96,
    "abbr": "IND",
    "ast": 121,
    "blk": 16,
    "fga": 581,
    "fgm": 250,
    "fpts": "1129.28",
    "fta": 123,
    "ftm": 105,
    "gp": 30,
    "min": 1440,
    "pace": 697.5,
    "pts": 703,
    "reb": 166,
    "stl": 48,
    "team": "Indiana Pacers",
    "to": 86,
    "usg": "21.14"
  },
  {
    "3pa": 229,
    "3pm": 81,
    "abbr": "MIL",
    "ast": 122,
    "blk": 8,
    "fga": 514,
    "fgm": 223,
    "fpts": "1050.13",
    "fta": 126,
    "ftm": 101,
    "gp": 27,
    "min": 1296,
    "pace": 615,
    "pts": 629,
    "reb": 166,
    "stl": 40,
    "team": "Milwaukee Bucks",
    "to": 62,
    "usg": "20.73"
  },
  {
    "3pa": 208,
    "3pm": 81,
    "abbr": "ATL",
    "ast": 119,
    "blk": 18,
    "fga": 566,
    "fgm": 257,
    "fpts": "1138.57",
    "fta": 121,
    "ftm": 94,
    "gp": 29,
    "min": 1392,
    "pace": 681.5,
    "pts": 690,
    "reb": 168,
    "stl": 56,
    "team": "Atlanta Hawks",
    "to": 84,
    "usg": "21.34"
  },
  {
    "3pa": 238,
    "3pm": 83,
    "abbr": "CHA",
    "ast": 120,
    "blk": 16,
    "fga": 533,
    "fgm": 227,
    "fpts": "1038.37",
    "fta": 97,
    "ftm": 80,
    "gp": 28,
    "min": 1344,
    "pace": 618.5,
    "pts": 619,
    "reb": 164,
    "stl": 33,
    "team": "Charlotte Hornets",
    "to": 57,
    "usg": "20.01"
  },
  {
    "3pa": 183,
    "3pm": 62,
    "abbr": "MIA",
    "ast": 109,
    "blk": 17,
    "fga": 529,
    "fgm": 220,
    "fpts": "1035.42",
    "fta": 133,
    "ftm": 115,
    "gp": 28,
    "min": 1344,
    "pace": 628.5,
    "pts": 619,
    "reb": 171,
    "stl": 37,
    "team": "Miami Heat",
    "to": 63,
    "usg": "20.43"
  },
  {
    "3pa": 200,
    "3pm": 66,
    "abbr": "ORL",
    "ast": 131,
    "blk": 18,
    "fga": 547,
    "fgm": 241,
    "fpts": "1154.96",
    "fta": 107,
    "ftm": 90,
    "gp": 31,
    "min": 1488,
    "pace": 635.5,
    "pts": 639,
    "reb": 202,
    "stl": 54,
    "team": "Orlando Magic",
    "to": 69,
    "usg": "18.99"
  },
  {
    "3pa": 192,
    "3pm": 77,
    "abbr": "WAS",
    "ast": 144,
    "blk": 10,
    "fga": 471,
    "fgm": 207,
    "fpts": "1025.21",
    "fta": 125,
    "ftm": 104,
    "gp": 28,
    "min": 1344,
    "pace": 591.5,
    "pts": 597,
    "reb": 150,
    "stl": 46,
    "team": "Washington Wizards",
    "to": 84,
    "usg": "19.57"
  },
  {
    "3pa": 233,
    "3pm": 81,
    "abbr": "DAL",
    "ast": 146,
    "blk": 10,
    "fga": 486,
    "fgm": 197,
    "fpts": "1049.07",
    "fta": 126,
    "ftm": 102,
    "gp": 29,
    "min": 1392,
    "pace": 617,
    "pts": 578,
    "reb": 192,
    "stl": 44,
    "team": "Dallas Mavericks",
    "to": 89,
    "usg": "19.50"
  },
  {
    "3pa": 245,
    "3pm": 94,
    "abbr": "HOU",
    "ast": 123,
    "blk": 15,
    "fga": 555,
    "fgm": 237,
    "fpts": "1139.16",
    "fta": 125,
    "ftm": 101,
    "gp": 29,
    "min": 1392,
    "pace": 662.5,
    "pts": 670,
    "reb": 168,
    "stl": 62,
    "team": "Houston Rockets",
    "to": 76,
    "usg": "20.88"
  },
  {
    "3pa": 240,
    "3pm": 96,
    "abbr": "MEM",
    "ast": 104,
    "blk": 23,
    "fga": 567,
    "fgm": 245,
    "fpts": "1129.55",
    "fta": 167,
    "ftm": 132,
    "gp": 31,
    "min": 1488,
    "pace": 709.5,
    "pts": 720,
    "reb": 171,
    "stl": 38,
    "team": "Memphis Grizzlies",
    "to": 79,
    "usg": "20.26"
  },
  {
    "3pa": 250,
    "3pm": 100,
    "abbr": "NOP",
    "ast": 130,
    "blk": 15,
    "fga": 574,
    "fgm": 262,
    "fpts": "1178.28",
    "fta": 125,
    "ftm": 100,
    "gp": 31,
    "min": 1488,
    "pace": 686.5,
    "pts": 725,
    "reb": 180,
    "stl": 41,
    "team": "New Orleans Pelicans",
    "to": 76,
    "usg": "20.10"
  },
  {
    "3pa": 194,
    "3pm": 66,
    "abbr": "SAS",
    "ast": 132,
    "blk": 16,
    "fga": 507,
    "fgm": 216,
    "fpts": "1007.91",
    "fta": 132,
    "ftm": 105,
    "gp": 27,
    "min": 1296,
    "pace": 636,
    "pts": 604,
    "reb": 153,
    "stl": 38,
    "team": "San Antonio Spurs",
    "to": 90,
    "usg": "21.56"
  },
  {
    "3pa": 188,
    "3pm": 81,
    "abbr": "DEN",
    "ast": 133,
    "blk": 17,
    "fga": 604,
    "fgm": 281,
    "fpts": "1215.04",
    "fta": 154,
    "ftm": 126,
    "gp": 29,
    "min": 1392,
    "pace": 715,
    "pts": 770,
    "reb": 152,
    "stl": 43,
    "team": "Denver Nuggets",
    "to": 59,
    "usg": "22.26"
  },
  {
    "3pa": 209,
    "3pm": 66,
    "abbr": "MIN",
    "ast": 111,
    "blk": 24,
    "fga": 483,
    "fgm": 191,
    "fpts": "993.79",
    "fta": 124,
    "ftm": 107,
    "gp": 27,
    "min": 1296,
    "pace": 588,
    "pts": 556,
    "reb": 160,
    "stl": 47,
    "team": "Minnesota Timberwolves",
    "to": 66,
    "usg": "19.76"
  },
  {
    "3pa": 206,
    "3pm": 69,
    "abbr": "POR",
    "ast": 148,
    "blk": 19,
    "fga": 553,
    "fgm": 241,
    "fpts": "1225.42",
    "fta": 193,
    "ftm": 166,
    "gp": 31,
    "min": 1488,
    "pace": 692.5,
    "pts": 718,
    "reb": 188,
    "stl": 48,
    "team": "Portland Trail Blazers",
    "to": 77,
    "usg": "20.53"
  },
  {
    "3pa": 199,
    "3pm": 64,
    "abbr": "OKC",
    "ast": 117,
    "blk": 12,
    "fga": 521,
    "fgm": 211,
    "fpts": "963.11",
    "fta": 136,
    "ftm": 96,
    "gp": 28,
    "min": 1344,
    "pace": 649,
    "pts": 583,
    "reb": 151,
    "stl": 41,
    "team": "Oklahoma City Thunder",
    "to": 86,
    "usg": "21.00"
  },
  {
    "3pa": 178,
    "3pm": 76,
    "abbr": "UTA",
    "ast": 116,
    "blk": 10,
    "fga": 539,
    "fgm": 233,
    "fpts": "1072.77",
    "fta": 137,
    "ftm": 107,
    "gp": 30,
    "min": 1440,
    "pace": 645.5,
    "pts": 651,
    "reb": 178,
    "stl": 44,
    "team": "Utah Jazz",
    "to": 77,
    "usg": "19.85"
  },
  {
    "3pa": 218,
    "3pm": 69,
    "abbr": "GSW",
    "ast": 133,
    "blk": 16,
    "fga": 584,
    "fgm": 246,
    "fpts": "1124.59",
    "fta": 154,
    "ftm": 125,
    "gp": 30,
    "min": 1440,
    "pace": 720,
    "pts": 688,
    "reb": 181,
    "stl": 38,
    "team": "Golden State Warriors",
    "to": 90,
    "usg": "21.82"
  },
  {
    "3pa": 175,
    "3pm": 64,
    "abbr": "LAC",
    "ast": 105,
    "blk": 11,
    "fga": 530,
    "fgm": 233,
    "fpts": "1033.48",
    "fta": 140,
    "ftm": 118,
    "gp": 30,
    "min": 1440,
    "pace": 649,
    "pts": 649,
    "reb": 175,
    "stl": 35,
    "team": "Los Angeles Clippers",
    "to": 79,
    "usg": "19.59"
  },
  {
    "3pa": 257,
    "3pm": 102,
    "abbr": "LAL",
    "ast": 162,
    "blk": 14,
    "fga": 629,
    "fgm": 283,
    "fpts": "1320.16",
    "fta": 172,
    "ftm": 141,
    "gp": 32,
    "min": 1536,
    "pace": 763,
    "pts": 810,
    "reb": 179,
    "stl": 51,
    "team": "Los Angeles Lakers",
    "to": 81,
    "usg": "21.85"
  },
  {
    "3pa": 222,
    "3pm": 98,
    "abbr": "PHO",
    "ast": 105,
    "blk": 12,
    "fga": 556,
    "fgm": 259,
    "fpts": "1123.66",
    "fta": 145,
    "ftm": 117,
    "gp": 29,
    "min": 1392,
    "pace": 676.5,
    "pts": 735,
    "reb": 152,
    "stl": 47,
    "team": "Phoenix Suns",
    "to": 72,
    "usg": "20.88"
  },
  {
    "3pa": 254,
    "3pm": 92,
    "abbr": "SAC",
    "ast": 124,
    "blk": 19,
    "fga": 543,
    "fgm": 238,
    "fpts": "1134.72",
    "fta": 155,
    "ftm": 124,
    "gp": 29,
    "min": 1392,
    "pace": 680.5,
    "pts": 694,
    "reb": 181,
    "stl": 42,
    "team": "Sacramento Kings",
    "to": 87,
    "usg": "21.24"
  }
]