[
  {
    "3pa": 560,
    "3pm": 182,
    "abbr": "BOS",
    "ast": 313,
    "blk": 66,
    "fga": 1410,
    "fgm": 595,
    "fpts": "2955.44",
    "fta": 410,
    "ftm": 332,
    "gp": 80,
    "min": 3840,
    "pace": 1724,
    "pts": 1705,
    "reb": 509,
    "stl": 119,
    "team": "Boston Celtics",
    "to": 204,
    "usg": "19.77"
  },
  {
    "3pa": 558,
    "3pm": 215,
    "abbr": "BKN",
    "ast": 330,
    "blk": 44,
    "fga": 1545,
    "fgm": 669,
    "fpts": "3191.99",
    "fta": 372,
    "ftm": 309,
    "gp": 79,
    "min": 3792,
    "pace": 1824,
    "pts": 1863,
    "reb": 505,
    "stl": 164,
    "team": "Brooklyn Nets",
    "to": 189,
    "usg": "21.17"
  },
  {
    "3pa": 553,
    "3pm": 205,
    "abbr": "NYK",
    "ast": 318,
    "blk": 35,
    "fga": 1367,
    "fgm": 604,
    "fpts": "2961.54",
    "fta": 350,
    "ftm": 299,
    "gp": 77,
    "min": 3696,
    "pace": 1623,
    "pts": 1713,
    "reb": 535,
    "stl": 118,
    "team": "New York Knicks",
    "to": 180,
    "usg": "19.54"
  },
  {
    "3pa": 540,
    "3pm": 191,
    "abbr": "PHI",
    "ast": 359,
    "blk": 39,
    "fga": 1395,
    "fgm": 603,
    "fpts": "2959.78",
    "fta": 353,
    "ftm": 285,
    "gp": 78,
    "min": 3744,
    "pace": 1713.5,
    "pts": 1683,
    "reb": 493,
    "stl": 145,
    "team": "Philadelphia 76ers",
    "to": 225,
    "usg": "20.23"
  },
  {
    "3pa": 550,
    "3pm": 197,
    "abbr": "TOR",
    "ast": 314,
    "blk": 58,
    "fga": 1255,
    "fgm": 517,
    "fpts": "2594.35",
    "fta": 312,
    "ftm": 254,
    "gp": 76,
    "min": 3648,
    "pace": 1559,
    "pts": 1487,
    "reb": 410,
    "stl": 122,
    "team": "Toronto Raptors",
    "to": 220,
    "usg": "18.81"
  },
  {
    "3pa": 577,
    "3pm": 193,
    "abbr": "CHI",
    "ast": 358,
    "blk": 44,
    "fga": 1446,
    "fgm": 599,
    "fpts": "2874.24",
    "fta": 308,
    "ftm": 243,
    "gp": 79,
    "min": 3792,
    "pace": 1697,
    "pts": 1636,
    "reb": 466,
    "stl": 115,
    "team": "Chicago Bulls",
    "to": 180,
    "usg": "19.83"
  },
  {
    "3pa": 647,
    "3pm": 247,
    "abbr": "CLE",
    "ast": 401,
    "blk": 47,
    "fga": 1496,
    "fgm": 671,
    "fpts": "3254.20",
    "fta": 316,
    "ftm": 248,
    "gp": 80,
    "min": 3840,
    "pace": 1735,
    "pts": 1840,
    "reb": 522,
    "stl": 130,
    "team": "Cleveland Cavaliers",
    "to": 170,
    "usg": "20.18"
  },
  {
    "3pa": 511,
    "3pm": 173,
    "abbr": "DET",
    "ast": 330,
    "blk": 28,
    "fga": 1279,
    "fgm": 548,
    "fpts": "2652.80",
    "fta": 327,
    "ftm": 275,
    "gp": 76,
    "min": 3648,
    "pace": 1568.5,
    "pts": 1545,
    "reb": 459,
    "stl": 88,
    "team": "Detroit Pistons",
    "to": 175,
    "usg": "18.71"
  },
  {
    "3pa": 616,
    "3pm": 231,
    "abbr": "IND",
    "ast": 323,
    "blk": 49,
    "fga": 1377,
    "fgm": 577,
    "fpts": "2904.77",
    "fta": 372,
    "ftm": 311,
    "gp": 79,
    "min": 3792,
    "pace": 1697,
    "pts": 1698,
    "reb": 470,
    "stl": 138,
    "team": "Indiana Pacers",
    "to": 219,
    "usg": "19.69"
  },
  {
    "3pa": 609,
    "3pm": 215,
    "abbr": "MIL",
    "ast": 362,
    "blk": 38,
    "fga": 1358,
    "fgm": 593,
    "fpts": "2812.83",
    "fta": 323,
    "ftm": 257,
    "gp": 77,
    "min": 3696,
    "pace": 1654.5,
    "pts": 1660,
    "reb": 447,
    "stl": 104,
    "team": "Milwaukee Bucks",
    "to": 214,
    "usg": "19.84"
  },
  {
    "3pa": 593,
    "3pm": 211,
    "abbr": "ATL",
    "ast": 319,
    "blk": 47,
    "fga": 1377,
    "fgm": 578,
    "fpts": "2822.44",
    "fta": 287,
    "ftm": 228,
    "gp": 74,
    "min": 3552,
    "pace": 1613.5,
    "pts": 1596,
    "reb": 465,
    "stl": 142,
    "team": "Atlanta Hawks",
    "to": 190,
    "usg": "20.25"
  },
  {
    "3pa": 664,
    "3pm": 250,
    "abbr": "CHA",
    "ast": 381,
    "blk": 47,
    "fga": 1416,
    "fgm": 602,
    "fpts": "2991.83",
    "fta": 310,
    "ftm": 252,
    "gp": 78,
    "min": 3744,
    "pace": 1692,
    "pts": 1708,
    "reb": 496,
    "stl": 101,
    "team": "Charlotte Hornets",
    "to": 182,
    "usg": "19.87"
  },
  {
    "3pa": 472,
    "3pm": 144,
    "abbr": "MIA",
    "ast": 289,
    "blk": 45,
    "fga": 1376,
    "fgm": 548,
    "fpts": "2681.24",
    "fta": 365,
    "ftm": 318,
    "gp": 78,
    "min": 3744,
    "pace": 1680.5,
    "pts": 1559,
    "reb": 481,
    "stl": 109,
    "team": "Miami Heat",
    "to": 199,
    "usg": "19.56"
  },
  {
    "3pa": 552,
    "3pm": 201,
    "abbr": "ORL",
    "ast": 366,
    "blk": 40,
    "fga": 1404,
    "fgm": 626,
    "fpts": "2989.87",
    "fta": 310,
    "ftm": 254,
    "gp": 78,
    "min": 3744,
    "pace": 1690,
    "pts": 1707,
    "reb": 508,
    "stl": 124,
    "team": "Orlando Magic",
    "to": 208,
    "usg": "19.97"
  },
  {
    "3pa": 557,
    "3pm": 223,
    "abbr": "WAS",
    "ast": 346,
    "blk": 33,
    "fga": 1321,
    "fgm": 598,
    "fpts": "2845.32",
    "fta": 345,
    "ftm": 282,
    "gp": 77,
    "min": 3696,
    "pace": 1610.5,
    "pts": 1702,
    "reb": 433,
    "stl": 114,
    "team": "Washington Wizards",
    "to": 193,
    "usg": "19.26"
  },
  {
    "3pa": 571,
    "3pm": 209,
    "abbr": "DAL",
    "ast": 338,
    "blk": 31,
    "fga": 1340,
    "fgm": 589,
    "fpts": "2799.41",
    "fta": 329,
    "ftm": 269,
    "gp": 77,
    "min": 3696,
    "pace": 1672.5,
    "pts": 1657,
    "reb": 484,
    "stl": 108,
    "team": "Dallas Mavericks",
    "to": 226,
    "usg": "19.72"
  },
  {
    "3pa": 676,
    "3pm": 240,
    "abbr": "HOU",
    "ast": 357,
    "blk": 36,
    "fga": 1516,
    "fgm": 653,
    "fpts": "3109.11",
    "fta": 293,
    "ftm": 235,
    "gp": 80,
    "min": 3840,
    "pace": 1776.5,
    "pts": 1782,
    "reb": 510,
    "stl": 153,
    "team": "Houston Rockets",
    "to": 204,
    "usg": "20.49"
  },
  {
    "3pa": 596,
    "3pm": 218,
    "abbr": "MEM",
    "ast": 308,
    "blk": 50,
    "fga": 1288,
    "fgm": 559,
    "fpts": "2723.06",
    "fta": 371,
    "ftm": 296,
    "gp": 76,
    "min": 3648,
    "pace": 1598.5,
    "pts": 1633,
    "reb": 429,
    "stl": 101,
    "team": "Memphis Grizzlies",
    "to": 192,
    "usg": "19.13"
  },
  {
    "3pa": 628,
    "3pm": 240,
    "abbr": "NOP",
    "ast": 350,
    "blk": 42,
    "fga": 1380,
    "fgm": 623,
    "fpts": "2983.37",
    "fta": 293,
    "ftm": 244,
    "gp": 77,
    "min": 3696,
    "pace": 1646.5,
    "pts": 1733,
    "reb": 476,
    "stl": 126,
    "team": "New Orleans Pelicans",
    "to": 185,
    "usg": "19.58"
  },
  {
    "3pa": 528,
    "3pm": 192,
    "abbr": "SAS",
    "ast": 354,
    "blk": 44,
    "fga": 1449,
    "fgm": 623,
    "fpts": "2908.97",
    "fta": 290,
    "ftm": 230,
    "gp": 79,
    "min": 3792,
    "pace": 1713,
    "pts": 1670,
    "reb": 488,
    "stl": 118,
    "team": "San Antonio Spurs",
    "to": 205,
    "usg": "20.03"
  },
  {
    "3pa": 538,
    "3pm": 207,
    "abbr": "DEN",
    "ast": 375,
    "blk": 47,
    "fga": 1470,
    "fgm": 669,
    "fpts": "3102.00",
    "fta": 331,
    "ftm": 269,
    "gp": 77,
    "min": 3696,
    "pace": 1760.5,
    "pts": 1815,
    "reb": 450,
    "stl": 138,
    "team": "Denver Nuggets",
    "to": 189,
    "usg": "20.87"
  },
  {
    "3pa": 575,
    "3pm": 222,
    "abbr": "MIN",
    "ast": 330,
    "blk": 65,
    "fga": 1378,
    "fgm": 615,
    "fpts": "2950.90",
    "fta": 300,
    "ftm": 248,
    "gp": 79,
    "min": 3792,
    "pace": 1649,
    "pts": 1702,
    "reb": 479,
    "stl": 123,
    "team": "Minnesota Timberwolves",
    "to": 200,
    "usg": "19.19"
  },
  {
    "3pa": 494,
    "3pm": 179,
    "abbr": "POR",
    "ast": 329,
    "blk": 41,
    "fga": 1367,
    "fgm": 597,
    "fpts": "2907.32",
    "fta": 395,
    "ftm": 322,
    "gp": 78,
    "min": 3744,
    "pace": 1667.5,
    "pts": 1696,
    "reb": 473,
    "stl": 123,
    "team": "Portland Trail Blazers",
    "to": 182,
    "usg": "19.57"
  },
  {
    "3pa": 564,
    "3pm": 206,
    "abbr": "OKC",
    "ast": 368,
    "blk": 37,
    "fga": 1400,
    "fgm": 592,
    "fpts": "2893.29",
    "fta": 384,
    "ftm": 304,
    "gp": 78,
    "min": 3744,
    "pace": 1725,
    "pts": 1694,
    "reb": 437,
    "stl": 126,
    "team": "Oklahoma City Thunder",
    "to": 207,
    "usg": "20.27"
  },
  {
    "3pa": 466,
    "3pm": 175,
    "abbr": "UTA",
    "ast": 267,
    "blk": 30,
    "fga": 1318,
    "fgm": 581,
    "fpts": "2573.69",
    "fta": 295,
    "ftm": 239,
    "gp": 78,
    "min": 3744,
    "pace": 1588.5,
    "pts": 1577,
    "reb": 413,
    "stl": 115,
    "team": "Utah Jazz",
    "to": 193,
    "usg": "18.47"
  },
  {
    "3pa": 576,
    "3pm": 186,
    "abbr": "GSW",
    "ast": 363,
    "blk": 39,
    "fga": 1436,
    "fgm": 585,
    "fpts": "2937.48",
    "fta": 355,
    "ftm": 279,
    "gp": 80,
    "min": 3840,
    "pace": 1728.5,
    "pts": 1637,
    "reb": 505,
    "stl": 152,
    "team": "Golden State Warriors",
    "to": 235,
    "usg": "20.28"
  },
  {
    "3pa": 540,
    "3pm": 193,
    "abbr": "LAC",
    "ast": 325,
    "blk": 32,
    "fga": 1346,
    "fgm": 558,
    "fpts": "2778.72",
    "fta": 347,
    "ftm": 282,
    "gp": 78,
    "min": 3744,
    "pace": 1623.5,
    "pts": 1592,
    "reb": 518,
    "stl": 101,
    "team": "Los Angeles Clippers",
    "to": 191,
    "usg": "19.20"
  },
  {
    "3pa": 584,
    "3pm": 228,
    "abbr": "LAL",
    "ast": 360,
    "blk": 42,
    "fga": 1400,
    "fgm": 632,
    "fpts": "2902.38",
    "fta": 307,
    "ftm": 248,
    "gp": 77,
    "min": 3696,
    "pace": 1695.5,
    "pts": 1742,
    "reb": 415,
    "stl": 124,
    "team": "Los Angeles Lakers",
    "to": 213,
    "usg": "20.20"
  },
  {
    "3pa": 560,
    "3pm": 220,
    "abbr": "PHO",
    "ast": 341,
    "blk": 55,
    "fga": 1413,
    "fgm": 617,
    "fpts": "3004.64",
    "fta": 386,
    "ftm": 310,
    "gp": 77,
    "min": 3696,
    "pace": 1726,
    "pts": 1765,
    "reb": 464,
    "stl": 131,
    "team": "Phoenix Suns",
    "to": 204,
    "usg": "20.56"
  },
  {
    "3pa": 621,
    "3pm": 237,
    "abbr": "SAC",
    "ast": 324,
    "blk": 53,
    "fga": 1387,
    "fgm": 620,
    "fpts": "2960.58",
    "fta": 349,
    "ftm": 282,
    "gp": 76,
    "min": 3648,
    "pace": 1664.5,
    "pts": 1760,
    "reb": 470,
    "stl": 118,
    "team": "Sacramento Kings",
    "to": 193,
    "usg": "20.18"
  }
]