[
  {
    "3pa": 6,
    "3pm": 1,
    "abbr": "CHI",
    "ast": 4,
    "blk": 0,
    "fga": 17,
    "fgm": 5,
    "fpts": "32.54",
    "fta": 2,
    "ftm": 1,
    "gp": 1,
    "min": 48,
    "pace": 18,
    "pts": 14,
    "reb": 6,
    "stl": 2,
    "team": "Chicago Bulls",
    "to": 2,
    "usg": "17.67"
  },
  {
    "3pa": 2,
    "3pm": 2,
    "abbr": "CLE",
    "ast": 7,
    "blk": 4,
    "fga": 7,
    "fgm": 7,
    "fpts": "52.56",
    "fta": 0,
    "ftm": 0,
    "gp": 1,
    "min": 48,
    "pace": 9,
    "pts": 16,
    "reb": 16,
    "stl": 0,
    "team": "Cleveland Cavaliers",
    "to": 4,
    "usg": "11.09"
  },
  {
    "3pa": 8,
    "3pm": 4,
    "abbr": "MIL",
    "ast": 6,
    "blk": 0,
    "fga": 8,
    "fgm": 4,
    "fpts": "44.60",
    "fta": 4,
    "ftm": 2,
    "gp": 1,
    "min": 48,
    "pace": 10,
    "pts": 14,
    "reb": 18,
    "stl": 0,
    "team": "Milwaukee Bucks",
    "to": 0,
    "usg": "9.78"
  },
  {
    "3pa": 1,
    "3pm": 0,
    "abbr": "ATL",
    "ast": 3,
    "blk": 0,
    "fga": 9,
    "fgm": 6,
    "fpts": "35.54",
    "fta": 5,
    "ftm": 4,
    "gp": 1,
    "min": 48,
    "pace": 13.5,
    "pts": 18,
    "reb": 9,
    "stl": 1,
    "team": "Atlanta Hawks",
    "to": 4,
    "usg": "13.49"
  },
  {
    "3pa": 9,
    "3pm": 4,
    "abbr": "CHA",
    "ast": 0,
    "blk": 0,
    "fga": 12,
    "fgm": 5,
    "fpts": "28.35",
    "fta": 3,
    "ftm": 3,
    "gp": 1,
    "min": 48,
    "pace": 13.5,
    "pts": 19,
    "reb": 3,
    "stl": 2,
    "team": "Charlotte Hornets",
    "to": 1,
    "usg": "11.93"
  },
  {
    "3pa": 0,
    "3pm": 0,
    "abbr": "WAS",
    "ast": 0,
    "blk": 7,
    "fga": 14,
    "fgm": 7,
    "fpts": "44.09",
    "fta": 0,
    "ftm": 0,
    "gp": 1,
    "min": 48,
    "pace": 13,
    "pts": 14,
    "reb": 7,
    "stl": 3,
    "team": "Washington Wizards",
    "to": 0,
    "usg": "11.67"
  },
  {
    "3pa": 10,
    "3pm": 3,
    "abbr": "HOU",
    "ast": 3,
    "blk": 0,
    "fga": 17,
    "fgm": 5,
    "fpts": "32.81",
    "fta": 9,
    "ftm": 5,
    "gp": 1,
    "min": 48,
    "pace": 21.5,
    "pts": 19,
    "reb": 4,
    "stl": 0,
    "team": "Houston Rockets",
    "to": 1,
    "usg": "19.13"
  },
  {
    "3pa": 8,
    "3pm": 3,
    "abbr": "MEM",
    "ast": 4,
    "blk": 2,
    "fga": 19,
    "fgm": 8,
    "fpts": "46.47",
    "fta": 9,
    "ftm": 8,
    "gp": 1,
    "min": 48,
    "pace": 26.5,
    "pts": 29,
    "reb": 8,
    "stl": 0,
    "team": "Memphis Grizzlies",
    "to": 4,
    "usg": "23.57"
  },
  {
    "3pa": 0,
    "3pm": 0,
    "abbr": "SAS",
    "ast": 0,
    "blk": 0,
    "fga": 3,
    "fgm": 0,
    "fpts": "19.20",
    "fta": 7,
    "ftm": 7,
    "gp": 1,
    "min": 48,
    "pace": 6.5,
    "pts": 7,
    "reb": 3,
    "stl": 3,
    "team": "San Antonio Spurs",
    "to": 0,
    "usg": "5.07"
  },
  {
    "3pa": 2,
    "3pm": 0,
    "abbr": "DEN",
    "ast": 1,
    "blk": 1,
    "fga": 5,
    "fgm": 2,
    "fpts": "21.66",
    "fta": 0,
    "ftm": 0,
    "gp": 1,
    "min": 48,
    "pace": 6,
    "pts": 4,
    "reb": 11,
    "stl": 0,
    "team": "Denver Nuggets",
    "to": 1,
    "usg": "5.28"
  },
  {
    "3pa": 5,
    "3pm": 0,
    "abbr": "POR",
    "ast": 2,
    "blk": 2,
    "fga": 16,
    "fgm": 4,
    "fpts": "29.45",
    "fta": 4,
    "ftm": 3,
    "gp": 1,
    "min": 48,
    "pace": 18,
    "pts": 11,
    "reb": 6,
    "stl": 0,
    "team": "Portland Trail Blazers",
    "to": 1,
    "usg": "16.18"
  },
  {
    "3pa": 1,
    "3pm": 1,
    "abbr": "UTA",
    "ast": 1,
    "blk": 3,
    "fga": 1,
    "fgm": 1,
    "fpts": "23.67",
    "fta": 3,
    "ftm": 1,
    "gp": 1,
    "min": 48,
    "pace": 5.5,
    "pts": 6,
    "reb": 6,
    "stl": 1,
    "team": "Utah Jazz",
    "to": 3,
    "usg": "4.71"
  },
  {
    "3pa": 4,
    "3pm": 1,
    "abbr": "GSW",
    "ast": 4,
    "blk": 2,
    "fga": 18,
    "fgm": 7,
    "fpts": "35.34",
    "fta": 2,
    "ftm": 0,
    "gp": 1,
    "min": 48,
    "pace": 20,
    "pts": 17,
    "reb": 4,
    "stl": 1,
    "team": "Golden State Warriors",
    "to": 2,
    "usg": "18.50"
  },
  {
    "3pa": 8,
    "3pm": 3,
    "abbr": "LAC",
    "ast": 1,
    "blk": 0,
    "fga": 16,
    "fgm": 7,
    "fpts": "36.80",
    "fta": 5,
    "ftm": 3,
    "gp": 1,
    "min": 48,
    "pace": 18.5,
    "pts": 21,
    "reb": 10,
    "stl": 0,
    "team": "Los Angeles Clippers",
    "to": 0,
    "usg": "15.44"
  }
]