[
  {
    "AVGRTG": "103.11",
    "DEFRTG": "100.17",
    "OFFENSE": "BOS",
    "OFFRTG": "106.05",
    "OPPONENT": "ORL",
    "PACE": "97.86",
    "PPG": "104.76",
    "PPG-A": "93.24",
    "PTS": "99.00"
  },
  {
    "AVGRTG": "100.17",
    "DEFRTG": "104.15",
    "OFFENSE": "ORL",
    "OFFRTG": "96.19",
    "OPPONENT": "BOS",
    "PACE": "97.86",
    "PPG": "93.24",
    "PPG-A": "104.76",
    "PTS": "99.00"
  },
  {
    "AVGRTG": "102.14",
    "DEFRTG": "101.50",
    "OFFENSE": "DET",
    "OFFRTG": "102.78",
    "OPPONENT": "CHA",
    "PACE": "99.44",
    "PPG": "100.05",
    "PPG-A": "105.33",
    "PTS": "102.69"
  },
  {
    "AVGRTG": "102.18",
    "DEFRTG": "100.64",
    "OFFENSE": "CHA",
    "OFFRTG": "103.73",
    "OPPONENT": "DET",
    "PACE": "99.44",
    "PPG": "105.33",
    "PPG-A": "100.05",
    "PTS": "102.69"
  },
  {
    "AVGRTG": "104.69",
    "DEFRTG": "108.21",
    "OFFENSE": "DEN",
    "OFFRTG": "101.18",
    "OPPONENT": "BKN",
    "PACE": "105.54",
    "PPG": "106.24",
    "PPG-A": "105.70",
    "PTS": "105.97"
  },
  {
    "AVGRTG": "102.54",
    "DEFRTG": "105.44",
    "OFFENSE": "BKN",
    "OFFRTG": "99.65",
    "OPPONENT": "DEN",
    "PACE": "105.54",
    "PPG": "105.70",
    "PPG-A": "106.24",
    "PTS": "105.97"
  },
  {
    "AVGRTG": "99.68",
    "DEFRTG": "99.87",
    "OFFENSE": "MIA",
    "OFFRTG": "99.49",
    "OPPONENT": "ATL",
    "PACE": "99.80",
    "PPG": "97.10",
    "PPG-A": "100.14",
    "PTS": "98.62"
  },
  {
    "AVGRTG": "99.83",
    "DEFRTG": "101.49",
    "OFFENSE": "ATL",
    "OFFRTG": "98.17",
    "OPPONENT": "MIA",
    "PACE": "99.80",
    "PPG": "100.14",
    "PPG-A": "97.10",
    "PTS": "98.62"
  },
  {
    "AVGRTG": "103.75",
    "DEFRTG": "100.55",
    "OFFENSE": "POR",
    "OFFRTG": "106.94",
    "OPPONENT": "MIL",
    "PACE": "101.64",
    "PPG": "110.27",
    "PPG-A": "103.26",
    "PTS": "106.77"
  },
  {
    "AVGRTG": "105.74",
    "DEFRTG": "108.37",
    "OFFENSE": "MIL",
    "OFFRTG": "103.10",
    "OPPONENT": "POR",
    "PACE": "101.64",
    "PPG": "103.26",
    "PPG-A": "110.27",
    "PTS": "106.77"
  },
  {
    "AVGRTG": "107.50",
    "DEFRTG": "106.03",
    "OFFENSE": "CLE",
    "OFFRTG": "108.97",
    "OPPONENT": "NYK",
    "PACE": "100.94",
    "PPG": "110.32",
    "PPG-A": "104.30",
    "PTS": "107.31"
  },
  {
    "AVGRTG": "104.13",
    "DEFRTG": "104.64",
    "OFFENSE": "NYK",
    "OFFRTG": "103.63",
    "OPPONENT": "CLE",
    "PACE": "100.94",
    "PPG": "104.30",
    "PPG-A": "110.32",
    "PTS": "107.31"
  },
  {
    "AVGRTG": "104.59",
    "DEFRTG": "106.62",
    "OFFENSE": "LAL",
    "OFFRTG": "102.57",
    "OPPONENT": "HOU",
    "PACE": "101.74",
    "PPG": "104.91",
    "PPG-A": "111.14",
    "PTS": "108.03"
  },
  {
    "AVGRTG": "108.69",
    "DEFRTG": "107.55",
    "OFFENSE": "HOU",
    "OFFRTG": "109.84",
    "OPPONENT": "LAL",
    "PACE": "101.74",
    "PPG": "111.14",
    "PPG-A": "104.91",
    "PTS": "108.03"
  },
  {
    "AVGRTG": "102.31",
    "DEFRTG": "103.03",
    "OFFENSE": "SAC",
    "OFFRTG": "101.59",
    "OPPONENT": "DAL",
    "PACE": "97.71",
    "PPG": "102.35",
    "PPG-A": "92.30",
    "PTS": "97.33"
  },
  {
    "AVGRTG": "101.71",
    "DEFRTG": "105.94",
    "OFFENSE": "DAL",
    "OFFRTG": "97.49",
    "OPPONENT": "SAC",
    "PACE": "97.71",
    "PPG": "92.30",
    "PPG-A": "102.35",
    "PTS": "97.33"
  },
  {
    "AVGRTG": "102.95",
    "DEFRTG": "105.03",
    "OFFENSE": "IND",
    "OFFRTG": "100.88",
    "OPPONENT": "PHO",
    "PACE": "104.82",
    "PPG": "104.24",
    "PPG-A": "106.35",
    "PTS": "105.29"
  },
  {
    "AVGRTG": "102.36",
    "DEFRTG": "104.66",
    "OFFENSE": "PHO",
    "OFFRTG": "100.05",
    "OPPONENT": "IND",
    "PACE": "104.82",
    "PPG": "106.35",
    "PPG-A": "104.24",
    "PTS": "105.29"
  },
  {
    "AVGRTG": "106.42",
    "DEFRTG": "98.82",
    "OFFENSE": "GSW",
    "OFFRTG": "114.03",
    "OPPONENT": "LAC",
    "PACE": "102.95",
    "PPG": "120.19",
    "PPG-A": "108.73",
    "PTS": "114.46"
  },
  {
    "AVGRTG": "104.68",
    "DEFRTG": "101.18",
    "OFFENSE": "LAC",
    "OFFRTG": "108.19",
    "OPPONENT": "GSW",
    "PACE": "102.95",
    "PPG": "108.73",
    "PPG-A": "120.19",
    "PTS": "114.46"
  }
]