[
  {
    "3pa": 1269,
    "3pm": 441,
    "abbr": "BOS",
    "ast": 1102,
    "blk": 255,
    "fga": 4105,
    "fgm": 1858,
    "fpts": "9879.40",
    "fta": 1193,
    "ftm": 918,
    "gp": 48,
    "min": "11351.00",
    "pace": 4820.5,
    "pts": 5075,
    "reb": 2162,
    "stl": 351,
    "team": "Boston Celtics",
    "to": 655,
    "usg": "19.91"
  },
  {
    "3pa": 1368,
    "3pm": 507,
    "abbr": "BKN",
    "ast": 1125,
    "blk": 289,
    "fga": 4409,
    "fgm": 2058,
    "fpts": "10847.70",
    "fta": 1164,
    "ftm": 895,
    "gp": 48,
    "min": "11308.00",
    "pace": 5070,
    "pts": 5518,
    "reb": 2281,
    "stl": 471,
    "team": "Brooklyn Nets",
    "to": 615,
    "usg": "20.90"
  },
  {
    "3pa": 1380,
    "3pm": 483,
    "abbr": "NYK",
    "ast": 1133,
    "blk": 232,
    "fga": 4399,
    "fgm": 1989,
    "fpts": "10432.70",
    "fta": 1256,
    "ftm": 985,
    "gp": 50,
    "min": "11863.00",
    "pace": 5081,
    "pts": 5446,
    "reb": 2226,
    "stl": 387,
    "team": "New York Knicks",
    "to": 622,
    "usg": "20.05"
  },
  {
    "3pa": 1198,
    "3pm": 434,
    "abbr": "PHI",
    "ast": 1039,
    "blk": 235,
    "fga": 4021,
    "fgm": 1825,
    "fpts": "9654.10",
    "fta": 1189,
    "ftm": 897,
    "gp": 47,
    "min": "11138.00",
    "pace": 4776.5,
    "pts": 4981,
    "reb": 2098,
    "stl": 398,
    "team": "Philadelphia 76ers",
    "to": 669,
    "usg": "19.95"
  },
  {
    "3pa": 1343,
    "3pm": 488,
    "abbr": "TOR",
    "ast": 1088,
    "blk": 229,
    "fga": 4093,
    "fgm": 1864,
    "fpts": "9667.60",
    "fta": 1171,
    "ftm": 912,
    "gp": 49,
    "min": "11581.00",
    "pace": 4880.5,
    "pts": 5128,
    "reb": 2123,
    "stl": 313,
    "team": "Toronto Raptors",
    "to": 724,
    "usg": "19.66"
  },
  {
    "3pa": 1176,
    "3pm": 428,
    "abbr": "CHI",
    "ast": 1173,
    "blk": 242,
    "fga": 4219,
    "fgm": 1931,
    "fpts": "9842.10",
    "fta": 908,
    "ftm": 690,
    "gp": 49,
    "min": "11527.00",
    "pace": 4791,
    "pts": 4980,
    "reb": 2098,
    "stl": 364,
    "team": "Chicago Bulls",
    "to": 627,
    "usg": "19.55"
  },
  {
    "3pa": 1339,
    "3pm": 479,
    "abbr": "CLE",
    "ast": 1133,
    "blk": 233,
    "fga": 4130,
    "fgm": 1874,
    "fpts": "9675.90",
    "fta": 915,
    "ftm": 709,
    "gp": 47,
    "min": "11100.00",
    "pace": 4697.5,
    "pts": 4936,
    "reb": 2067,
    "stl": 357,
    "team": "Cleveland Cavaliers",
    "to": 620,
    "usg": "19.92"
  },
  {
    "3pa": 1149,
    "3pm": 425,
    "abbr": "DET",
    "ast": 1077,
    "blk": 203,
    "fga": 3859,
    "fgm": 1759,
    "fpts": "9283.50",
    "fta": 1051,
    "ftm": 823,
    "gp": 47,
    "min": "11022.00",
    "pace": 4558.5,
    "pts": 4766,
    "reb": 2005,
    "stl": 329,
    "team": "Detroit Pistons",
    "to": 568,
    "usg": "19.03"
  },
  {
    "3pa": 1390,
    "3pm": 483,
    "abbr": "IND",
    "ast": 1087,
    "blk": 248,
    "fga": 4038,
    "fgm": 1819,
    "fpts": "9780.70",
    "fta": 1127,
    "ftm": 891,
    "gp": 47,
    "min": "11146.00",
    "pace": 4779.5,
    "pts": 5012,
    "reb": 2136,
    "stl": 392,
    "team": "Indiana Pacers",
    "to": 705,
    "usg": "20.09"
  },
  {
    "3pa": 1399,
    "3pm": 502,
    "abbr": "MIL",
    "ast": 1147,
    "blk": 250,
    "fga": 3966,
    "fgm": 1785,
    "fpts": "9607.70",
    "fta": 1090,
    "ftm": 846,
    "gp": 47,
    "min": "11112.00",
    "pace": 4662,
    "pts": 4918,
    "reb": 2006,
    "stl": 355,
    "team": "Milwaukee Bucks",
    "to": 648,
    "usg": "19.70"
  },
  {
    "3pa": 1367,
    "3pm": 494,
    "abbr": "ATL",
    "ast": 1081,
    "blk": 247,
    "fga": 4193,
    "fgm": 1884,
    "fpts": "9770.10",
    "fta": 947,
    "ftm": 729,
    "gp": 48,
    "min": "11414.00",
    "pace": 4876.5,
    "pts": 4991,
    "reb": 2113,
    "stl": 426,
    "team": "Atlanta Hawks",
    "to": 724,
    "usg": "19.94"
  },
  {
    "3pa": 1501,
    "3pm": 532,
    "abbr": "CHA",
    "ast": 1163,
    "blk": 291,
    "fga": 4307,
    "fgm": 1923,
    "fpts": "10126.30",
    "fta": 910,
    "ftm": 711,
    "gp": 49,
    "min": "11596.00",
    "pace": 4897,
    "pts": 5089,
    "reb": 2179,
    "stl": 340,
    "team": "Charlotte Hornets",
    "to": 584,
    "usg": "19.58"
  },
  {
    "3pa": 1161,
    "3pm": 401,
    "abbr": "MIA",
    "ast": 1001,
    "blk": 257,
    "fga": 4170,
    "fgm": 1872,
    "fpts": "9670.70",
    "fta": 1103,
    "ftm": 859,
    "gp": 49,
    "min": "11600.00",
    "pace": 4839.5,
    "pts": 5004,
    "reb": 2191,
    "stl": 320,
    "team": "Miami Heat",
    "to": 618,
    "usg": "19.32"
  },
  {
    "3pa": 1290,
    "3pm": 466,
    "abbr": "ORL",
    "ast": 1136,
    "blk": 263,
    "fga": 4296,
    "fgm": 1988,
    "fpts": "10354.80",
    "fta": 1098,
    "ftm": 840,
    "gp": 50,
    "min": "11801.00",
    "pace": 4972,
    "pts": 5282,
    "reb": 2264,
    "stl": 371,
    "team": "Orlando Magic",
    "to": 616,
    "usg": "19.56"
  },
  {
    "3pa": 1307,
    "3pm": 472,
    "abbr": "WAS",
    "ast": 1096,
    "blk": 207,
    "fga": 4047,
    "fgm": 1853,
    "fpts": "9556.40",
    "fta": 1148,
    "ftm": 860,
    "gp": 48,
    "min": "11356.00",
    "pace": 4830,
    "pts": 5038,
    "reb": 2037,
    "stl": 366,
    "team": "Washington Wizards",
    "to": 716,
    "usg": "19.83"
  },
  {
    "3pa": 1170,
    "3pm": 462,
    "abbr": "DAL",
    "ast": 983,
    "blk": 164,
    "fga": 3719,
    "fgm": 1746,
    "fpts": "9038.30",
    "fta": 1104,
    "ftm": 850,
    "gp": 48,
    "min": "11343.00",
    "pace": 4575,
    "pts": 4804,
    "reb": 2119,
    "stl": 303,
    "team": "Dallas Mavericks",
    "to": 717,
    "usg": "18.50"
  },
  {
    "3pa": 1463,
    "3pm": 521,
    "abbr": "HOU",
    "ast": 1189,
    "blk": 256,
    "fga": 4537,
    "fgm": 2089,
    "fpts": "10740.30",
    "fta": 1181,
    "ftm": 917,
    "gp": 52,
    "min": "12277.00",
    "pace": 5335.5,
    "pts": 5616,
    "reb": 2209,
    "stl": 458,
    "team": "Houston Rockets",
    "to": 738,
    "usg": "20.16"
  },
  {
    "3pa": 1412,
    "3pm": 480,
    "abbr": "MEM",
    "ast": 982,
    "blk": 261,
    "fga": 3927,
    "fgm": 1716,
    "fpts": "9486.20",
    "fta": 1426,
    "ftm": 1064,
    "gp": 50,
    "min": "11939.00",
    "pace": 4892,
    "pts": 4976,
    "reb": 2121,
    "stl": 335,
    "team": "Memphis Grizzlies",
    "to": 700,
    "usg": "18.69"
  },
  {
    "3pa": 1466,
    "3pm": 522,
    "abbr": "NOP",
    "ast": 1156,
    "blk": 234,
    "fga": 4399,
    "fgm": 1957,
    "fpts": "10376.20",
    "fta": 996,
    "ftm": 769,
    "gp": 49,
    "min": "11685.00",
    "pace": 5021,
    "pts": 5205,
    "reb": 2411,
    "stl": 358,
    "team": "New Orleans Pelicans",
    "to": 640,
    "usg": "20.06"
  },
  {
    "3pa": 1190,
    "3pm": 402,
    "abbr": "SAS",
    "ast": 1023,
    "blk": 199,
    "fga": 3991,
    "fgm": 1777,
    "fpts": "9134.10",
    "fta": 1031,
    "ftm": 806,
    "gp": 48,
    "min": "11316.00",
    "pace": 4704.5,
    "pts": 4762,
    "reb": 1978,
    "stl": 363,
    "team": "San Antonio Spurs",
    "to": 660,
    "usg": "19.24"
  },
  {
    "3pa": 1189,
    "3pm": 442,
    "abbr": "DEN",
    "ast": 1119,
    "blk": 243,
    "fga": 4148,
    "fgm": 1964,
    "fpts": "9919.30",
    "fta": 1091,
    "ftm": 861,
    "gp": 47,
    "min": "11105.00",
    "pace": 4789.5,
    "pts": 5231,
    "reb": 1894,
    "stl": 392,
    "team": "Denver Nuggets",
    "to": 533,
    "usg": "19.92"
  },
  {
    "3pa": 1249,
    "3pm": 444,
    "abbr": "MIN",
    "ast": 1060,
    "blk": 244,
    "fga": 3954,
    "fgm": 1856,
    "fpts": "9517.40",
    "fta": 1124,
    "ftm": 870,
    "gp": 48,
    "min": "11341.00",
    "pace": 4733,
    "pts": 5026,
    "reb": 1932,
    "stl": 379,
    "team": "Minnesota Timberwolves",
    "to": 663,
    "usg": "19.26"
  },
  {
    "3pa": 1296,
    "3pm": 493,
    "abbr": "POR",
    "ast": 1048,
    "blk": 262,
    "fga": 4211,
    "fgm": 1903,
    "fpts": "10255.00",
    "fta": 1351,
    "ftm": 1075,
    "gp": 49,
    "min": "11601.00",
    "pace": 5012.5,
    "pts": 5374,
    "reb": 2210,
    "stl": 386,
    "team": "Portland Trail Blazers",
    "to": 639,
    "usg": "19.96"
  },
  {
    "3pa": 1226,
    "3pm": 431,
    "abbr": "OKC",
    "ast": 1062,
    "blk": 263,
    "fga": 4242,
    "fgm": 1925,
    "fpts": "9913.40",
    "fta": 1169,
    "ftm": 877,
    "gp": 49,
    "min": "11597.00",
    "pace": 4994.5,
    "pts": 5158,
    "reb": 2052,
    "stl": 413,
    "team": "Oklahoma City Thunder",
    "to": 652,
    "usg": "19.86"
  },
  {
    "3pa": 1110,
    "3pm": 396,
    "abbr": "UTA",
    "ast": 865,
    "blk": 174,
    "fga": 4044,
    "fgm": 1759,
    "fpts": "8851.50",
    "fta": 997,
    "ftm": 765,
    "gp": 49,
    "min": "11535.00",
    "pace": 4627.5,
    "pts": 4679,
    "reb": 2000,
    "stl": 342,
    "team": "Utah Jazz",
    "to": 557,
    "usg": "18.47"
  },
  {
    "3pa": 1378,
    "3pm": 443,
    "abbr": "GSW",
    "ast": 1061,
    "blk": 183,
    "fga": 4319,
    "fgm": 1874,
    "fpts": "9626.70",
    "fta": 1108,
    "ftm": 841,
    "gp": 48,
    "min": "11340.00",
    "pace": 5019,
    "pts": 5032,
    "reb": 2061,
    "stl": 429,
    "team": "Golden State Warriors",
    "to": 694,
    "usg": "20.64"
  },
  {
    "3pa": 1207,
    "3pm": 421,
    "abbr": "LAC",
    "ast": 1077,
    "blk": 168,
    "fga": 4097,
    "fgm": 1838,
    "fpts": "9506.50",
    "fta": 1159,
    "ftm": 889,
    "gp": 48,
    "min": "11317.00",
    "pace": 4798.5,
    "pts": 4986,
    "reb": 2070,
    "stl": 349,
    "team": "Los Angeles Clippers",
    "to": 613,
    "usg": "19.71"
  },
  {
    "3pa": 1401,
    "3pm": 513,
    "abbr": "LAL",
    "ast": 1272,
    "blk": 275,
    "fga": 4402,
    "fgm": 2100,
    "fpts": "11003.40",
    "fta": 1199,
    "ftm": 906,
    "gp": 51,
    "min": "11967.00",
    "pace": 5138.5,
    "pts": 5619,
    "reb": 2272,
    "stl": 439,
    "team": "Los Angeles Lakers",
    "to": 678,
    "usg": "20.15"
  },
  {
    "3pa": 1231,
    "3pm": 479,
    "abbr": "PHO",
    "ast": 1068,
    "blk": 265,
    "fga": 4085,
    "fgm": 1920,
    "fpts": "10037.80",
    "fta": 1348,
    "ftm": 1062,
    "gp": 48,
    "min": "11392.00",
    "pace": 4999,
    "pts": 5381,
    "reb": 2069,
    "stl": 380,
    "team": "Phoenix Suns",
    "to": 718,
    "usg": "20.18"
  },
  {
    "3pa": 1441,
    "3pm": 539,
    "abbr": "SAC",
    "ast": 1146,
    "blk": 266,
    "fga": 3999,
    "fgm": 1857,
    "fpts": "10075.20",
    "fta": 1215,
    "ftm": 946,
    "gp": 49,
    "min": "11639.00",
    "pace": 4799.5,
    "pts": 5199,
    "reb": 2091,
    "stl": 402,
    "team": "Sacramento Kings",
    "to": 688,
    "usg": "19.24"
  }
]