[
  {
    "D-RT": "110",
    "EFG%": "56.56%",
    "O-RT": "111",
    "OPP": "IND",
    "PLAYER": "Evan Fournier",
    "PLAYERID": "13913",
    "POS": "SG",
    "POW-AST": "13.27%",
    "POW-BLK": "0.00%",
    "POW-PTS": "18.77%",
    "POW-REB": "6.48%",
    "POW-STL": "16.67%",
    "SALARY": "5700.00",
    "SCHEDULE_ID": "35452",
    "TEAM": "ORL",
    "TS%": "60.33%",
    "USG%": "22.72%"
  },
  {
    "D-RT": "108",
    "EFG%": "44.82%",
    "O-RT": "100",
    "OPP": "IND",
    "PLAYER": "Elfrid Payton",
    "PLAYERID": "18602",
    "POS": "PG",
    "POW-AST": "27.04%",
    "POW-BLK": "13.04%",
    "POW-PTS": "11.43%",
    "POW-REB": "6.74%",
    "POW-STL": "11.11%",
    "SALARY": "5400.00",
    "SCHEDULE_ID": "35452",
    "TEAM": "ORL",
    "TS%": "50.56%",
    "USG%": "21.04%"
  },
  {
    "D-RT": "105",
    "EFG%": "52.21%",
    "O-RT": "114",
    "OPP": "IND",
    "PLAYER": "Aaron Gordon",
    "PLAYERID": "18601",
    "POS": "SF",
    "POW-AST": "11.22%",
    "POW-BLK": "17.39%",
    "POW-PTS": "11.67%",
    "POW-REB": "12.69%",
    "POW-STL": "25.93%",
    "SALARY": "5600.00",
    "SCHEDULE_ID": "35452",
    "TEAM": "ORL",
    "TS%": "54.38%",
    "USG%": "18.29%"
  },
  {
    "D-RT": "105",
    "EFG%": "52.50%",
    "O-RT": "108",
    "OPP": "IND",
    "PLAYER": "Serge Ibaka",
    "PLAYERID": "1294",
    "POS": "PF",
    "POW-AST": "2.04%",
    "POW-BLK": "21.74%",
    "POW-PTS": "13.48%",
    "POW-REB": "12.69%",
    "POW-STL": "1.85%",
    "SALARY": "5200.00",
    "SCHEDULE_ID": "35452",
    "TEAM": "ORL",
    "TS%": "55.46%",
    "USG%": "18.60%"
  },
  {
    "D-RT": "105",
    "EFG%": "44.20%",
    "O-RT": "106",
    "OPP": "IND",
    "PLAYER": "Nikola Vucevic",
    "PLAYERID": "13296",
    "POS": "C",
    "POW-AST": "15.31%",
    "POW-BLK": "6.52%",
    "POW-PTS": "13.72%",
    "POW-REB": "24.87%",
    "POW-STL": "12.96%",
    "SALARY": "7100.00",
    "SCHEDULE_ID": "35452",
    "TEAM": "ORL",
    "TS%": "50.40%",
    "USG%": "21.85%"
  },
  {
    "D-RT": "101",
    "EFG%": "54.35%",
    "O-RT": "118",
    "OPP": "IND",
    "PLAYER": "Bismack Biyombo",
    "PLAYERID": "13312",
    "POS": "C",
    "POW-AST": "3.06%",
    "POW-BLK": "28.26%",
    "POW-PTS": "3.49%",
    "POW-REB": "16.58%",
    "POW-STL": "1.85%",
    "SALARY": "4200.00",
    "SCHEDULE_ID": "35452",
    "TEAM": "ORL",
    "TS%": "56.36%",
    "USG%": "11.81%"
  },
  {
    "D-RT": "109",
    "EFG%": "51.77%",
    "O-RT": "103",
    "OPP": "IND",
    "PLAYER": "Jeff Green",
    "PLAYERID": "1314",
    "POS": "SF",
    "POW-AST": "5.10%",
    "POW-BLK": "8.70%",
    "POW-PTS": "9.51%",
    "POW-REB": "9.07%",
    "POW-STL": "3.70%",
    "SALARY": "3800.00",
    "SCHEDULE_ID": "35452",
    "TEAM": "ORL",
    "TS%": "53.25%",
    "USG%": "19.75%"
  },
  {
    "D-RT": "111",
    "EFG%": "50.30%",
    "O-RT": "113",
    "OPP": "IND",
    "PLAYER": "D.J. Augustin",
    "PLAYERID": "1064",
    "POS": "PG",
    "POW-AST": "13.27%",
    "POW-BLK": "0.00%",
    "POW-PTS": "9.87%",
    "POW-REB": "1.30%",
    "POW-STL": "5.56%",
    "SALARY": "3600.00",
    "SCHEDULE_ID": "35452",
    "TEAM": "ORL",
    "TS%": "56.30%",
    "USG%": "23.79%"
  },
  {
    "D-RT": "109",
    "EFG%": "46.67%",
    "O-RT": "97",
    "OPP": "IND",
    "PLAYER": "Mario Hezonja",
    "PLAYERID": "18923",
    "POS": "SG",
    "POW-AST": "4.08%",
    "POW-BLK": "4.35%",
    "POW-PTS": "6.02%",
    "POW-REB": "4.92%",
    "POW-STL": "7.41%",
    "SALARY": "3500.00",
    "SCHEDULE_ID": "35452",
    "TEAM": "ORL",
    "TS%": "51.84%",
    "USG%": "23.43%"
  },
  {
    "D-RT": "116",
    "EFG%": "47.65%",
    "O-RT": "102",
    "OPP": "IND",
    "PLAYER": "Damjan Rudez",
    "PLAYERID": "18590",
    "POS": "SF",
    "POW-AST": "0.51%",
    "POW-BLK": "0.00%",
    "POW-PTS": "0.36%",
    "POW-REB": "0.78%",
    "POW-STL": "5.56%",
    "SALARY": "3500.00",
    "SCHEDULE_ID": "35452",
    "TEAM": "ORL",
    "TS%": "50.31%",
    "USG%": "6.19%"
  },
  {
    "D-RT": "101",
    "EFG%": "53.95%",
    "O-RT": "106",
    "OPP": "ORL",
    "PLAYER": "Paul George",
    "PLAYERID": "1245",
    "POS": "SF",
    "POW-AST": "11.65%",
    "POW-BLK": "6.56%",
    "POW-PTS": "18.17%",
    "POW-REB": "14.35%",
    "POW-STL": "16.16%",
    "SALARY": "8600.00",
    "SCHEDULE_ID": "35452",
    "TEAM": "IND",
    "TS%": "56.60%",
    "USG%": "26.53%"
  },
  {
    "D-RT": "103",
    "EFG%": "47.54%",
    "O-RT": "99",
    "OPP": "ORL",
    "PLAYER": "Monta Ellis",
    "PLAYERID": "1088",
    "POS": "SG",
    "POW-AST": "19.68%",
    "POW-BLK": "4.92%",
    "POW-PTS": "9.87%",
    "POW-REB": "9.09%",
    "POW-STL": "16.16%",
    "SALARY": "5600.00",
    "SCHEDULE_ID": "35452",
    "TEAM": "IND",
    "TS%": "52.79%",
    "USG%": "17.38%"
  },
  {
    "D-RT": "104",
    "EFG%": "42.93%",
    "O-RT": "105",
    "OPP": "ORL",
    "PLAYER": "Jeff Teague",
    "PLAYERID": "1005",
    "POS": "PG",
    "POW-AST": "25.70%",
    "POW-BLK": "3.28%",
    "POW-PTS": "13.10%",
    "POW-REB": "6.46%",
    "POW-STL": "17.17%",
    "SALARY": "6200.00",
    "SCHEDULE_ID": "35452",
    "TEAM": "IND",
    "TS%": "46.11%",
    "USG%": "25.20%"
  },
  {
    "D-RT": "107",
    "EFG%": "56.92%",
    "O-RT": "104",
    "OPP": "ORL",
    "PLAYER": "Thaddeus Young",
    "PLAYERID": "1289",
    "POS": "PF",
    "POW-AST": "8.43%",
    "POW-BLK": "6.56%",
    "POW-PTS": "9.32%",
    "POW-REB": "14.35%",
    "POW-STL": "14.14%",
    "SALARY": "5400.00",
    "SCHEDULE_ID": "35452",
    "TEAM": "IND",
    "TS%": "58.59%",
    "USG%": "14.91%"
  },
  {
    "D-RT": "101",
    "EFG%": "52.78%",
    "O-RT": "103",
    "OPP": "ORL",
    "PLAYER": "Myles Turner",
    "PLAYERID": "18915",
    "POS": "C",
    "POW-AST": "4.42%",
    "POW-BLK": "40.98%",
    "POW-PTS": "14.02%",
    "POW-REB": "16.75%",
    "POW-STL": "11.11%",
    "SALARY": "6600.00",
    "SCHEDULE_ID": "35452",
    "TEAM": "IND",
    "TS%": "57.60%",
    "USG%": "21.02%"
  },
  {
    "D-RT": "104",
    "EFG%": "51.01%",
    "O-RT": "104",
    "OPP": "ORL",
    "PLAYER": "C.J. Miles",
    "PLAYERID": "1299",
    "POS": "SF",
    "POW-AST": "3.61%",
    "POW-BLK": "11.48%",
    "POW-PTS": "13.19%",
    "POW-REB": "7.42%",
    "POW-STL": "10.10%",
    "SALARY": "4400.00",
    "SCHEDULE_ID": "35452",
    "TEAM": "IND",
    "TS%": "53.82%",
    "USG%": "20.06%"
  },
  {
    "D-RT": "109",
    "EFG%": "53.21%",
    "O-RT": "99",
    "OPP": "ORL",
    "PLAYER": "Aaron Brooks",
    "PLAYERID": "1047",
    "POS": "PG",
    "POW-AST": "8.43%",
    "POW-BLK": "4.92%",
    "POW-PTS": "3.97%",
    "POW-REB": "1.20%",
    "POW-STL": "3.03%",
    "SALARY": "3500.00",
    "SCHEDULE_ID": "35452",
    "TEAM": "IND",
    "TS%": "56.02%",
    "USG%": "20.55%"
  },
  {
    "D-RT": "102",
    "EFG%": "47.16%",
    "O-RT": "105",
    "OPP": "ORL",
    "PLAYER": "Al Jefferson",
    "PLAYERID": "1496",
    "POS": "C",
    "POW-AST": "4.82%",
    "POW-BLK": "8.20%",
    "POW-PTS": "7.20%",
    "POW-REB": "12.44%",
    "POW-STL": "3.03%",
    "SALARY": "4000.00",
    "SCHEDULE_ID": "35452",
    "TEAM": "IND",
    "TS%": "51.24%",
    "USG%": "23.09%"
  },
  {
    "D-RT": "104",
    "EFG%": "56.88%",
    "O-RT": "110",
    "OPP": "ORL",
    "PLAYER": "Lavoy Allen",
    "PLAYERID": "13331",
    "POS": "PF",
    "POW-AST": "5.62%",
    "POW-BLK": "8.20%",
    "POW-PTS": "2.03%",
    "POW-REB": "6.94%",
    "POW-STL": "3.03%",
    "SALARY": "3500.00",
    "SCHEDULE_ID": "35452",
    "TEAM": "IND",
    "TS%": "59.55%",
    "USG%": "10.23%"
  },
  {
    "D-RT": "105",
    "EFG%": "49.78%",
    "O-RT": "102",
    "OPP": "ORL",
    "PLAYER": "Glenn Robinson",
    "PLAYERID": "18621",
    "POS": "SF",
    "POW-AST": "2.01%",
    "POW-BLK": "3.28%",
    "POW-PTS": "3.14%",
    "POW-REB": "3.59%",
    "POW-STL": "3.03%",
    "SALARY": "3600.00",
    "SCHEDULE_ID": "35452",
    "TEAM": "IND",
    "TS%": "53.54%",
    "USG%": "17.44%"
  },
  {
    "D-RT": "107",
    "EFG%": "46.50%",
    "O-RT": "114",
    "OPP": "NYK",
    "PLAYER": "Harrison Barnes",
    "PLAYERID": "13901",
    "POS": "SF",
    "POW-AST": "4.67%",
    "POW-BLK": "3.57%",
    "POW-PTS": "23.29%",
    "POW-REB": "14.85%",
    "POW-STL": "4.35%",
    "SALARY": "6000.00",
    "SCHEDULE_ID": "35453",
    "TEAM": "DAL",
    "TS%": "49.19%",
    "USG%": "22.24%"
  },
  {
    "D-RT": "109",
    "EFG%": "58.11%",
    "O-RT": "105",
    "OPP": "NYK",
    "PLAYER": "Wesley Matthews",
    "PLAYERID": "1339",
    "POS": "SG",
    "POW-AST": "12.00%",
    "POW-BLK": "3.57%",
    "POW-PTS": "11.33%",
    "POW-REB": "6.06%",
    "POW-STL": "15.94%",
    "SALARY": "4700.00",
    "SCHEDULE_ID": "35453",
    "TEAM": "DAL",
    "TS%": "60.18%",
    "USG%": "18.73%"
  },
  {
    "D-RT": "109",
    "EFG%": "55.16%",
    "O-RT": "105",
    "OPP": "NYK",
    "PLAYER": "Deron Williams",
    "PLAYERID": "1080",
    "POS": "PG",
    "POW-AST": "19.33%",
    "POW-BLK": "7.14%",
    "POW-PTS": "9.65%",
    "POW-REB": "3.33%",
    "POW-STL": "5.80%",
    "SALARY": "6300.00",
    "SCHEDULE_ID": "35453",
    "TEAM": "DAL",
    "TS%": "57.13%",
    "USG%": "21.45%"
  },
  {
    "D-RT": "111",
    "EFG%": "43.53%",
    "O-RT": "106",
    "OPP": "NYK",
    "PLAYER": "J.J. Barea",
    "PLAYERID": "18605",
    "POS": "PG",
    "POW-AST": "26.00%",
    "POW-BLK": "3.57%",
    "POW-PTS": "15.57%",
    "POW-REB": "8.48%",
    "POW-STL": "7.25%",
    "SALARY": "5800.00",
    "SCHEDULE_ID": "35453",
    "TEAM": "DAL",
    "TS%": "49.90%",
    "USG%": "23.52%"
  },
  {
    "D-RT": "106",
    "EFG%": "47.21%",
    "O-RT": "110",
    "OPP": "NYK",
    "PLAYER": "Dirk Nowitzki",
    "PLAYERID": "1346",
    "POS": "PF",
    "POW-AST": "2.00%",
    "POW-BLK": "10.71%",
    "POW-PTS": "4.63%",
    "POW-REB": "6.06%",
    "POW-STL": "4.35%",
    "SALARY": "6500.00",
    "SCHEDULE_ID": "35453",
    "TEAM": "DAL",
    "TS%": "58.20%",
    "USG%": "21.83%"
  },
  {
    "D-RT": "99",
    "EFG%": "48.91%",
    "O-RT": "120",
    "OPP": "NYK",
    "PLAYER": "Andrew Bogut",
    "PLAYERID": "1494",
    "POS": "C",
    "POW-AST": "7.33%",
    "POW-BLK": "14.29%",
    "POW-PTS": "2.83%",
    "POW-REB": "19.70%",
    "POW-STL": "4.35%",
    "SALARY": "4400.00",
    "SCHEDULE_ID": "35453",
    "TEAM": "DAL",
    "TS%": "51.27%",
    "USG%": "12.21%"
  },
  {
    "D-RT": "112",
    "EFG%": "48.98%",
    "O-RT": "114",
    "OPP": "NYK",
    "PLAYER": "Seth Curry",
    "PLAYERID": "16825",
    "POS": "SG",
    "POW-AST": "14.00%",
    "POW-BLK": "10.71%",
    "POW-PTS": "8.88%",
    "POW-REB": "4.55%",
    "POW-STL": "17.39%",
    "SALARY": "4200.00",
    "SCHEDULE_ID": "35453",
    "TEAM": "DAL",
    "TS%": "53.54%",
    "USG%": "17.26%"
  },
  {
    "D-RT": "104",
    "EFG%": "50.90%",
    "O-RT": "103",
    "OPP": "NYK",
    "PLAYER": "Justin Anderson",
    "PLAYERID": "18927",
    "POS": "SF",
    "POW-AST": "6.67%",
    "POW-BLK": "14.29%",
    "POW-PTS": "8.49%",
    "POW-REB": "10.91%",
    "POW-STL": "10.14%",
    "SALARY": "3900.00",
    "SCHEDULE_ID": "35453",
    "TEAM": "DAL",
    "TS%": "53.56%",
    "USG%": "19.22%"
  },
  {
    "D-RT": "104",
    "EFG%": "53.81%",
    "O-RT": "114",
    "OPP": "NYK",
    "PLAYER": "Dwight Powell",
    "PLAYERID": "18566",
    "POS": "PF",
    "POW-AST": "4.00%",
    "POW-BLK": "14.29%",
    "POW-PTS": "6.56%",
    "POW-REB": "11.52%",
    "POW-STL": "18.84%",
    "SALARY": "4100.00",
    "SCHEDULE_ID": "35453",
    "TEAM": "DAL",
    "TS%": "60.18%",
    "USG%": "13.01%"
  },
  {
    "D-RT": "&nbsp;",
    "EFG%": "&nbsp;",
    "O-RT": "&nbsp;",
    "PLAYER": "Dorian Finney-Smith",
    "PLAYERID": "&nbsp;",
    "POS": "SF",
    "POW-AST": "0.67%",
    "POW-BLK": "3.57%",
    "POW-PTS": "2.19%",
    "POW-REB": "3.03%",
    "POW-STL": "5.80%",
    "SALARY": "-1",
    "TEAM": "DAL",
    "TS%": "&nbsp;",
    "USG%": "8.36%"
  },
  {
    "D-RT": "107",
    "EFG%": "50.29%",
    "O-RT": "107",
    "OPP": "DAL",
    "PLAYER": "Carmelo Anthony",
    "PLAYERID": "1091",
    "POS": "SF",
    "POW-AST": "12.63%",
    "POW-BLK": "3.92%",
    "POW-PTS": "22.03%",
    "POW-REB": "12.91%",
    "POW-STL": "11.29%",
    "SALARY": "7800.00",
    "SCHEDULE_ID": "35453",
    "TEAM": "NYK",
    "TS%": "53.30%",
    "USG%": "29.08%"
  },
  {
    "D-RT": "110",
    "EFG%": "45.41%",
    "O-RT": "96",
    "OPP": "DAL",
    "PLAYER": "Derrick Rose",
    "PLAYERID": "1086",
    "POS": "PG",
    "POW-AST": "22.63%",
    "POW-BLK": "7.84%",
    "POW-PTS": "15.70%",
    "POW-REB": "9.62%",
    "POW-STL": "9.68%",
    "SALARY": "6000.00",
    "SCHEDULE_ID": "35453",
    "TEAM": "NYK",
    "TS%": "50.28%",
    "USG%": "26.51%"
  },
  {
    "D-RT": "103",
    "EFG%": "53.29%",
    "O-RT": "103",
    "OPP": "DAL",
    "PLAYER": "Kristaps Porzingis",
    "PLAYERID": "18899",
    "POS": "PF",
    "POW-AST": "4.74%",
    "POW-BLK": "25.49%",
    "POW-PTS": "18.43%",
    "POW-REB": "14.43%",
    "POW-STL": "8.06%",
    "SALARY": "6800.00",
    "SCHEDULE_ID": "35453",
    "TEAM": "NYK",
    "TS%": "54.89%",
    "USG%": "22.96%"
  },
  {
    "D-RT": "109",
    "EFG%": "47.62%",
    "O-RT": "109",
    "OPP": "DAL",
    "PLAYER": "Courtney Lee",
    "PLAYERID": "1025",
    "POS": "SG",
    "POW-AST": "5.79%",
    "POW-BLK": "7.84%",
    "POW-PTS": "9.81%",
    "POW-REB": "6.33%",
    "POW-STL": "9.68%",
    "SALARY": "3700.00",
    "SCHEDULE_ID": "35453",
    "TEAM": "NYK",
    "TS%": "51.66%",
    "USG%": "13.82%"
  },
  {
    "D-RT": "101",
    "EFG%": "44.99%",
    "O-RT": "98",
    "OPP": "DAL",
    "PLAYER": "Joakim Noah",
    "PLAYERID": "1404",
    "POS": "C",
    "POW-AST": "18.42%",
    "POW-BLK": "13.73%",
    "POW-PTS": "4.69%",
    "POW-REB": "20.00%",
    "POW-STL": "14.52%",
    "SALARY": "4700.00",
    "SCHEDULE_ID": "35453",
    "TEAM": "NYK",
    "TS%": "48.09%",
    "USG%": "12.95%"
  },
  {
    "D-RT": "108",
    "EFG%": "45.38%",
    "O-RT": "105",
    "OPP": "DAL",
    "PLAYER": "Brandon Jennings",
    "PLAYERID": "924",
    "POS": "PG",
    "POW-AST": "21.58%",
    "POW-BLK": "0.00%",
    "POW-PTS": "6.87%",
    "POW-REB": "6.84%",
    "POW-STL": "8.06%",
    "SALARY": "4100.00",
    "SCHEDULE_ID": "35453",
    "TEAM": "NYK",
    "TS%": "49.21%",
    "USG%": "20.14%"
  },
  {
    "D-RT": "112",
    "EFG%": "44.89%",
    "O-RT": "107",
    "OPP": "DAL",
    "PLAYER": "Lance Thomas",
    "PLAYERID": "13363",
    "POS": "SF",
    "POW-AST": "1.58%",
    "POW-BLK": "1.96%",
    "POW-PTS": "3.38%",
    "POW-REB": "4.81%",
    "POW-STL": "8.06%",
    "SALARY": "3500.00",
    "SCHEDULE_ID": "35453",
    "TEAM": "NYK",
    "TS%": "47.10%",
    "USG%": "12.64%"
  },
  {
    "D-RT": "105",
    "EFG%": "54.38%",
    "O-RT": "94",
    "OPP": "DAL",
    "PLAYER": "Justin Holiday",
    "PLAYERID": "14559",
    "POS": "SG",
    "POW-AST": "3.68%",
    "POW-BLK": "9.80%",
    "POW-PTS": "4.58%",
    "POW-REB": "4.30%",
    "POW-STL": "4.84%",
    "SALARY": "3500.00",
    "SCHEDULE_ID": "35453",
    "TEAM": "NYK",
    "TS%": "57.09%",
    "USG%": "15.47%"
  },
  {
    "D-RT": "&nbsp;",
    "EFG%": "&nbsp;",
    "O-RT": "&nbsp;",
    "PLAYER": "Mindaugas Kuzminskas",
    "PLAYERID": "&nbsp;",
    "POS": "SF",
    "POW-AST": "1.58%",
    "POW-BLK": "0.00%",
    "POW-PTS": "3.27%",
    "POW-REB": "3.04%",
    "POW-STL": "4.84%",
    "SALARY": "-1",
    "TEAM": "NYK",
    "TS%": "&nbsp;",
    "USG%": "19.77%"
  },
  {
    "D-RT": "102",
    "EFG%": "49.26%",
    "O-RT": "102",
    "OPP": "DAL",
    "PLAYER": "Kyle O'Quinn",
    "PLAYERID": "13934",
    "POS": "C",
    "POW-AST": "2.63%",
    "POW-BLK": "19.61%",
    "POW-PTS": "4.69%",
    "POW-REB": "6.84%",
    "POW-STL": "4.84%",
    "SALARY": "3500.00",
    "SCHEDULE_ID": "35453",
    "TEAM": "NYK",
    "TS%": "55.70%",
    "USG%": "19.51%"
  },
  {
    "D-RT": "106",
    "EFG%": "53.57%",
    "O-RT": "105",
    "OPP": "DET",
    "PLAYER": "Victor Oladipo",
    "PLAYERID": "16807",
    "POS": "SG",
    "POW-AST": "7.69%",
    "POW-BLK": "4.65%",
    "POW-PTS": "15.72%",
    "POW-REB": "8.08%",
    "POW-STL": "8.00%",
    "SALARY": "5400.00",
    "SCHEDULE_ID": "35454",
    "TEAM": "OKC",
    "TS%": "57.56%",
    "USG%": "21.34%"
  },
  {
    "D-RT": "103",
    "EFG%": "45.88%",
    "O-RT": "115",
    "OPP": "DET",
    "PLAYER": "Russell Westbrook",
    "PLAYERID": "1083",
    "POS": "PG",
    "POW-AST": "46.70%",
    "POW-BLK": "11.63%",
    "POW-PTS": "29.92%",
    "POW-REB": "19.24%",
    "POW-STL": "16.00%",
    "SALARY": "11600.00",
    "SCHEDULE_ID": "35454",
    "TEAM": "OKC",
    "TS%": "52.16%",
    "USG%": "44.67%"
  },
  {
    "D-RT": "105",
    "EFG%": "48.61%",
    "O-RT": "123",
    "OPP": "DET",
    "PLAYER": "Steven Adams",
    "PLAYERID": "16848",
    "POS": "C",
    "POW-AST": "4.95%",
    "POW-BLK": "20.93%",
    "POW-PTS": "9.90%",
    "POW-REB": "17.34%",
    "POW-STL": "22.67%",
    "SALARY": "5100.00",
    "SCHEDULE_ID": "35454",
    "TEAM": "OKC",
    "TS%": "51.96%",
    "USG%": "14.41%"
  },
  {
    "D-RT": "106",
    "EFG%": "44.98%",
    "O-RT": "119",
    "OPP": "DET",
    "PLAYER": "Andre Roberson",
    "PLAYERID": "16849",
    "POS": "SF",
    "POW-AST": "5.49%",
    "POW-BLK": "16.28%",
    "POW-PTS": "6.03%",
    "POW-REB": "10.93%",
    "POW-STL": "17.33%",
    "SALARY": "3800.00",
    "SCHEDULE_ID": "35454",
    "TEAM": "OKC",
    "TS%": "47.18%",
    "USG%": "10.87%"
  },
  {
    "D-RT": "&nbsp;",
    "EFG%": "&nbsp;",
    "O-RT": "&nbsp;",
    "PLAYER": "Domantas Sabonis",
    "PLAYERID": "&nbsp;",
    "POS": "PF",
    "POW-AST": "8.79%",
    "POW-BLK": "6.98%",
    "POW-PTS": "7.75%",
    "POW-REB": "7.84%",
    "POW-STL": "5.33%",
    "SALARY": "-1",
    "TEAM": "OKC",
    "TS%": "&nbsp;",
    "USG%": "15.48%"
  },
  {
    "D-RT": "105",
    "EFG%": "47.52%",
    "O-RT": "123",
    "OPP": "DET",
    "PLAYER": "Enes Kanter",
    "PLAYERID": "13299",
    "POS": "PF",
    "POW-AST": "1.10%",
    "POW-BLK": "9.30%",
    "POW-PTS": "11.63%",
    "POW-REB": "14.96%",
    "POW-STL": "5.33%",
    "SALARY": "5000.00",
    "SCHEDULE_ID": "35454",
    "TEAM": "OKC",
    "TS%": "53.62%",
    "USG%": "26.09%"
  },
  {
    "D-RT": "108",
    "EFG%": "53.70%",
    "O-RT": "100",
    "OPP": "DET",
    "PLAYER": "Jerami Grant",
    "PLAYERID": "18576",
    "POS": "SF",
    "POW-AST": "1.10%",
    "POW-BLK": "27.91%",
    "POW-PTS": "5.17%",
    "POW-REB": "4.75%",
    "POW-STL": "1.33%",
    "SALARY": "3500.00",
    "SCHEDULE_ID": "35454",
    "TEAM": "OKC",
    "TS%": "57.73%",
    "USG%": "17.15%"
  },
  {
    "D-RT": "&nbsp;",
    "EFG%": "&nbsp;",
    "O-RT": "&nbsp;",
    "PLAYER": "Semaj Christon",
    "PLAYERID": "&nbsp;",
    "POS": "PG",
    "POW-AST": "14.84%",
    "POW-BLK": "2.33%",
    "POW-PTS": "4.52%",
    "POW-REB": "3.56%",
    "POW-STL": "5.33%",
    "SALARY": "-1",
    "TEAM": "OKC",
    "TS%": "&nbsp;",
    "USG%": "18.04%"
  },
  {
    "D-RT": "108",
    "EFG%": "57.95%",
    "O-RT": "102",
    "OPP": "DET",
    "PLAYER": "Kyle Singler",
    "PLAYERID": "13321",
    "POS": "SF",
    "POW-AST": "0.55%",
    "POW-BLK": "4.65%",
    "POW-PTS": "2.26%",
    "POW-REB": "3.09%",
    "POW-STL": "1.33%",
    "SALARY": "3500.00",
    "SCHEDULE_ID": "35454",
    "TEAM": "OKC",
    "TS%": "62.54%",
    "USG%": "12.58%"
  },
  {
    "D-RT": "109",
    "EFG%": "51.51%",
    "O-RT": "111",
    "OPP": "DET",
    "PLAYER": "Joffrey Lauvergne",
    "PLAYERID": "18756",
    "POS": "C",
    "POW-AST": "3.85%",
    "POW-BLK": "2.33%",
    "POW-PTS": "2.80%",
    "POW-REB": "5.23%",
    "POW-STL": "6.67%",
    "SALARY": "3500.00",
    "SCHEDULE_ID": "35454",
    "TEAM": "OKC",
    "TS%": "54.80%",
    "USG%": "15.03%"
  },
  {
    "D-RT": "107",
    "EFG%": "50.43%",
    "O-RT": "107",
    "OPP": "OKC",
    "PLAYER": "Kentavious Caldwell-Pope",
    "PLAYERID": "16869",
    "POS": "SG",
    "POW-AST": "11.50%",
    "POW-BLK": "0.00%",
    "POW-PTS": "13.20%",
    "POW-REB": "6.55%",
    "POW-STL": "18.75%",
    "SALARY": "4700.00",
    "SCHEDULE_ID": "35454",
    "TEAM": "DET",
    "TS%": "55.18%",
    "USG%": "16.99%"
  },
  {
    "D-RT": "107",
    "EFG%": "56.32%",
    "O-RT": "112",
    "OPP": "OKC",
    "PLAYER": "Tobias Harris",
    "PLAYERID": "13332",
    "POS": "PF",
    "POW-AST": "8.00%",
    "POW-BLK": "17.50%",
    "POW-PTS": "16.89%",
    "POW-REB": "10.61%",
    "POW-STL": "11.25%",
    "SALARY": "5800.00",
    "SCHEDULE_ID": "35454",
    "TEAM": "DET",
    "TS%": "61.34%",
    "USG%": "21.16%"
  },
  {
    "D-RT": "108",
    "EFG%": "49.39%",
    "O-RT": "107",
    "OPP": "OKC",
    "PLAYER": "Marcus Morris",
    "PLAYERID": "13316",
    "POS": "SF",
    "POW-AST": "9.00%",
    "POW-BLK": "7.50%",
    "POW-PTS": "15.56%",
    "POW-REB": "9.93%",
    "POW-STL": "15.00%",
    "SALARY": "5600.00",
    "SCHEDULE_ID": "35454",
    "TEAM": "DET",
    "TS%": "53.69%",
    "USG%": "20.53%"
  },
  {
    "D-RT": "98",
    "EFG%": "48.65%",
    "O-RT": "103",
    "OPP": "OKC",
    "PLAYER": "Andre Drummond",
    "PLAYERID": "13904",
    "POS": "C",
    "POW-AST": "6.50%",
    "POW-BLK": "30.00%",
    "POW-PTS": "15.25%",
    "POW-REB": "32.28%",
    "POW-STL": "17.50%",
    "SALARY": "8100.00",
    "SCHEDULE_ID": "35454",
    "TEAM": "DET",
    "TS%": "50.76%",
    "USG%": "22.34%"
  },
  {
    "D-RT": "110",
    "EFG%": "54.71%",
    "O-RT": "98",
    "OPP": "OKC",
    "PLAYER": "Ish Smith",
    "PLAYERID": "13958",
    "POS": "PG",
    "POW-AST": "33.50%",
    "POW-BLK": "5.00%",
    "POW-PTS": "9.83%",
    "POW-REB": "5.42%",
    "POW-STL": "16.25%",
    "SALARY": "5300.00",
    "SCHEDULE_ID": "35454",
    "TEAM": "DET",
    "TS%": "56.12%",
    "USG%": "22.93%"
  },
  {
    "D-RT": "106",
    "EFG%": "47.16%",
    "O-RT": "107",
    "OPP": "OKC",
    "PLAYER": "Jon Leuer",
    "PLAYERID": "13317",
    "POS": "PF",
    "POW-AST": "4.50%",
    "POW-BLK": "20.00%",
    "POW-PTS": "10.54%",
    "POW-REB": "14.67%",
    "POW-STL": "5.00%",
    "SALARY": "4400.00",
    "SCHEDULE_ID": "35454",
    "TEAM": "DET",
    "TS%": "51.17%",
    "USG%": "15.14%"
  },
  {
    "D-RT": "109",
    "EFG%": "50.69%",
    "O-RT": "97",
    "OPP": "OKC",
    "PLAYER": "Beno Udrih",
    "PLAYERID": "1050",
    "POS": "PG",
    "POW-AST": "17.50%",
    "POW-BLK": "0.00%",
    "POW-PTS": "7.57%",
    "POW-REB": "3.61%",
    "POW-STL": "3.75%",
    "SALARY": "3500.00",
    "SCHEDULE_ID": "35454",
    "TEAM": "DET",
    "TS%": "53.26%",
    "USG%": "22.95%"
  },
  {
    "D-RT": "106",
    "EFG%": "53.03%",
    "O-RT": "91",
    "OPP": "OKC",
    "PLAYER": "Stanley Johnson",
    "PLAYERID": "18913",
    "POS": "SF",
    "POW-AST": "5.50%",
    "POW-BLK": "5.00%",
    "POW-PTS": "4.71%",
    "POW-REB": "6.09%",
    "POW-STL": "5.00%",
    "SALARY": "3500.00",
    "SCHEDULE_ID": "35454",
    "TEAM": "DET",
    "TS%": "56.66%",
    "USG%": "15.16%"
  },
  {
    "D-RT": "104",
    "EFG%": "43.95%",
    "O-RT": "114",
    "OPP": "OKC",
    "PLAYER": "Aron Baynes",
    "PLAYERID": "14114",
    "POS": "C",
    "POW-AST": "1.00%",
    "POW-BLK": "15.00%",
    "POW-PTS": "4.61%",
    "POW-REB": "8.13%",
    "POW-STL": "6.25%",
    "SALARY": "3500.00",
    "SCHEDULE_ID": "35454",
    "TEAM": "DET",
    "TS%": "46.53%",
    "USG%": "13.04%"
  },
  {
    "D-RT": "108",
    "EFG%": "51.88%",
    "O-RT": "103",
    "OPP": "OKC",
    "PLAYER": "Darrun Hilliard",
    "PLAYERID": "18914",
    "POS": "SG",
    "POW-AST": "2.50%",
    "POW-BLK": "0.00%",
    "POW-PTS": "0.31%",
    "POW-REB": "0.45%",
    "POW-STL": "0.00%",
    "SALARY": "3500.00",
    "SCHEDULE_ID": "35454",
    "TEAM": "DET",
    "TS%": "56.33%",
    "USG%": "18.53%"
  },
  {
    "D-RT": "106",
    "EFG%": "51.91%",
    "O-RT": "105",
    "OPP": "NOP",
    "PLAYER": "Avery Bradley",
    "PLAYERID": "941",
    "POS": "SG",
    "POW-AST": "15.02%",
    "POW-BLK": "7.84%",
    "POW-PTS": "17.04%",
    "POW-REB": "19.62%",
    "POW-STL": "16.18%",
    "SALARY": "7000.00",
    "SCHEDULE_ID": "35455",
    "TEAM": "BOS",
    "TS%": "53.85%",
    "USG%": "21.80%"
  },
  {
    "D-RT": "107",
    "EFG%": "49.64%",
    "O-RT": "113",
    "OPP": "NOP",
    "PLAYER": "Isaiah Thomas",
    "PLAYERID": "13344",
    "POS": "PG",
    "POW-AST": "25.75%",
    "POW-BLK": "1.96%",
    "POW-PTS": "23.82%",
    "POW-REB": "6.72%",
    "POW-STL": "14.71%",
    "SALARY": "8100.00",
    "SCHEDULE_ID": "35455",
    "TEAM": "BOS",
    "TS%": "53.92%",
    "USG%": "32.11%"
  },
  {
    "D-RT": "103",
    "EFG%": "58.50%",
    "O-RT": "101",
    "OPP": "NOP",
    "PLAYER": "Marcus Smart",
    "PLAYERID": "18567",
    "POS": "PG",
    "POW-AST": "9.44%",
    "POW-BLK": "3.92%",
    "POW-PTS": "7.70%",
    "POW-REB": "6.18%",
    "POW-STL": "8.82%",
    "SALARY": "5100.00",
    "SCHEDULE_ID": "35455",
    "TEAM": "BOS",
    "TS%": "61.44%",
    "USG%": "20.00%"
  },
  {
    "D-RT": "101",
    "EFG%": "56.68%",
    "O-RT": "113",
    "OPP": "NOP",
    "PLAYER": "Al Horford",
    "PLAYERID": "1499",
    "POS": "C",
    "POW-AST": "6.01%",
    "POW-BLK": "13.73%",
    "POW-PTS": "3.70%",
    "POW-REB": "4.30%",
    "POW-STL": "1.47%",
    "SALARY": "6700.00",
    "SCHEDULE_ID": "35455",
    "TEAM": "BOS",
    "TS%": "59.18%",
    "USG%": "17.39%"
  },
  {
    "D-RT": "103",
    "EFG%": "49.06%",
    "O-RT": "110",
    "OPP": "NOP",
    "PLAYER": "Kelly Olynyk",
    "PLAYERID": "16845",
    "POS": "C",
    "POW-AST": "3.43%",
    "POW-BLK": "1.96%",
    "POW-PTS": "3.80%",
    "POW-REB": "5.11%",
    "POW-STL": "1.47%",
    "SALARY": "4000.00",
    "SCHEDULE_ID": "35455",
    "TEAM": "BOS",
    "TS%": "50.31%",
    "USG%": "20.57%"
  },
  {
    "D-RT": "102",
    "EFG%": "51.91%",
    "O-RT": "113",
    "OPP": "NOP",
    "PLAYER": "Jae Crowder",
    "PLAYERID": "13942",
    "POS": "SF",
    "POW-AST": "3.43%",
    "POW-BLK": "7.84%",
    "POW-PTS": "5.54%",
    "POW-REB": "6.72%",
    "POW-STL": "7.35%",
    "SALARY": "5900.00",
    "SCHEDULE_ID": "35455",
    "TEAM": "BOS",
    "TS%": "54.86%",
    "USG%": "17.88%"
  },
  {
    "D-RT": "102",
    "EFG%": "56.88%",
    "O-RT": "117",
    "OPP": "NOP",
    "PLAYER": "Amir Johnson",
    "PLAYERID": "1285",
    "POS": "PF",
    "POW-AST": "9.01%",
    "POW-BLK": "13.73%",
    "POW-PTS": "7.39%",
    "POW-REB": "10.48%",
    "POW-STL": "10.29%",
    "SALARY": "4200.00",
    "SCHEDULE_ID": "35455",
    "TEAM": "BOS",
    "TS%": "58.46%",
    "USG%": "14.97%"
  },
  {
    "D-RT": "107",
    "EFG%": "48.25%",
    "O-RT": "81",
    "OPP": "NOP",
    "PLAYER": "Terry Rozier",
    "PLAYERID": "18894",
    "POS": "PG",
    "POW-AST": "7.30%",
    "POW-BLK": "1.96%",
    "POW-PTS": "5.95%",
    "POW-REB": "7.53%",
    "POW-STL": "10.29%",
    "SALARY": "3700.00",
    "SCHEDULE_ID": "35455",
    "TEAM": "BOS",
    "TS%": "51.48%",
    "USG%": "15.58%"
  },
  {
    "D-RT": "105",
    "EFG%": "45.76%",
    "O-RT": "106",
    "OPP": "NOP",
    "PLAYER": "Tyler Zeller",
    "PLAYERID": "13911",
    "POS": "C",
    "POW-AST": "6.01%",
    "POW-BLK": "23.53%",
    "POW-PTS": "7.49%",
    "POW-REB": "11.83%",
    "POW-STL": "5.88%",
    "SALARY": "4000.00",
    "SCHEDULE_ID": "35455",
    "TEAM": "BOS",
    "TS%": "49.54%",
    "USG%": "17.72%"
  },
  {
    "D-RT": "&nbsp;",
    "EFG%": "50.32%",
    "O-RT": "&nbsp;",
    "PLAYER": "Jaylen Brown",
    "PLAYERID": "&nbsp;",
    "POS": "SF",
    "POW-AST": "3.86%",
    "POW-BLK": "9.80%",
    "POW-PTS": "6.47%",
    "POW-REB": "5.91%",
    "POW-STL": "8.82%",
    "SALARY": "-1",
    "TEAM": "BOS",
    "TS%": "51.14%",
    "USG%": "18.79%"
  },
  {
    "D-RT": "104",
    "EFG%": "51.34%",
    "O-RT": "110",
    "OPP": "BOS",
    "PLAYER": "Anthony Davis",
    "PLAYERID": "13895",
    "POS": "PF",
    "POW-AST": "8.15%",
    "POW-BLK": "45.45%",
    "POW-PTS": "30.90%",
    "POW-REB": "25.12%",
    "POW-STL": "22.89%",
    "SALARY": "11500.00",
    "SCHEDULE_ID": "35455",
    "TEAM": "NOP",
    "TS%": "56.03%",
    "USG%": "31.59%"
  },
  {
    "D-RT": "109",
    "EFG%": "54.04%",
    "O-RT": "105",
    "OPP": "BOS",
    "PLAYER": "E'Twaun Moore",
    "PLAYERID": "18582",
    "POS": "SG",
    "POW-AST": "12.45%",
    "POW-BLK": "6.06%",
    "POW-PTS": "12.34%",
    "POW-REB": "3.72%",
    "POW-STL": "10.84%",
    "SALARY": "4500.00",
    "SCHEDULE_ID": "35455",
    "TEAM": "NOP",
    "TS%": "56.31%",
    "USG%": "18.99%"
  },
  {
    "D-RT": "109",
    "EFG%": "48.39%",
    "O-RT": "103",
    "OPP": "BOS",
    "PLAYER": "Tim Frazier",
    "PLAYERID": "18743",
    "POS": "PG",
    "POW-AST": "34.76%",
    "POW-BLK": "3.03%",
    "POW-PTS": "11.35%",
    "POW-REB": "8.14%",
    "POW-STL": "12.05%",
    "SALARY": "5500.00",
    "SCHEDULE_ID": "35455",
    "TEAM": "NOP",
    "TS%": "51.56%",
    "USG%": "21.42%"
  },
  {
    "D-RT": "103",
    "EFG%": "46.70%",
    "O-RT": "110",
    "OPP": "BOS",
    "PLAYER": "Solomon Hill",
    "PLAYERID": "16863",
    "POS": "SF",
    "POW-AST": "10.73%",
    "POW-BLK": "6.06%",
    "POW-PTS": "4.94%",
    "POW-REB": "8.14%",
    "POW-STL": "16.87%",
    "SALARY": "3700.00",
    "SCHEDULE_ID": "35455",
    "TEAM": "NOP",
    "TS%": "49.12%",
    "USG%": "12.26%"
  },
  {
    "D-RT": "109",
    "EFG%": "50.79%",
    "O-RT": "104",
    "OPP": "BOS",
    "PLAYER": "Terrence Jones",
    "PLAYERID": "13912",
    "POS": "PF",
    "POW-AST": "5.58%",
    "POW-BLK": "13.64%",
    "POW-PTS": "6.91%",
    "POW-REB": "9.77%",
    "POW-STL": "10.84%",
    "SALARY": "4300.00",
    "SCHEDULE_ID": "35455",
    "TEAM": "NOP",
    "TS%": "55.84%",
    "USG%": "18.36%"
  },
  {
    "D-RT": "112",
    "EFG%": "46.14%",
    "O-RT": "109",
    "OPP": "BOS",
    "PLAYER": "Dante Cunningham",
    "PLAYERID": "1259",
    "POS": "SF",
    "POW-AST": "2.58%",
    "POW-BLK": "6.06%",
    "POW-PTS": "5.03%",
    "POW-REB": "7.21%",
    "POW-STL": "6.02%",
    "SALARY": "3500.00",
    "SCHEDULE_ID": "35455",
    "TEAM": "NOP",
    "TS%": "49.81%",
    "USG%": "12.80%"
  },
  {
    "D-RT": "&nbsp;",
    "EFG%": "&nbsp;",
    "O-RT": "&nbsp;",
    "PLAYER": "Buddy Hield",
    "PLAYERID": "&nbsp;",
    "POS": "SG",
    "POW-AST": "3.86%",
    "POW-BLK": "3.03%",
    "POW-PTS": "10.07%",
    "POW-REB": "6.98%",
    "POW-STL": "7.23%",
    "SALARY": "-1",
    "TEAM": "NOP",
    "TS%": "&nbsp;",
    "USG%": "24.76%"
  },
  {
    "D-RT": "108",
    "EFG%": "47.51%",
    "O-RT": "105",
    "OPP": "BOS",
    "PLAYER": "Langston Galloway",
    "PLAYERID": "18717",
    "POS": "PG",
    "POW-AST": "6.87%",
    "POW-BLK": "1.52%",
    "POW-PTS": "7.21%",
    "POW-REB": "6.51%",
    "POW-STL": "9.64%",
    "SALARY": "3700.00",
    "SCHEDULE_ID": "35455",
    "TEAM": "NOP",
    "TS%": "51.72%",
    "USG%": "20.41%"
  },
  {
    "D-RT": "108",
    "EFG%": "51.48%",
    "O-RT": "106",
    "OPP": "BOS",
    "PLAYER": "Omer Asik",
    "PLAYERID": "1457",
    "POS": "C",
    "POW-AST": "2.58%",
    "POW-BLK": "9.09%",
    "POW-PTS": "3.16%",
    "POW-REB": "15.35%",
    "POW-STL": "0.00%",
    "SALARY": "3500.00",
    "SCHEDULE_ID": "35455",
    "TEAM": "NOP",
    "TS%": "56.69%",
    "USG%": "9.83%"
  },
  {
    "D-RT": "107",
    "EFG%": "50.34%",
    "O-RT": "100",
    "OPP": "BOS",
    "PLAYER": "Alexis Ajinca",
    "PLAYERID": "17095",
    "POS": "C",
    "POW-AST": "0.00%",
    "POW-BLK": "3.03%",
    "POW-PTS": "1.68%",
    "POW-REB": "4.19%",
    "POW-STL": "1.20%",
    "SALARY": "3500.00",
    "SCHEDULE_ID": "35455",
    "TEAM": "NOP",
    "TS%": "54.53%",
    "USG%": "12.59%"
  },
  {
    "D-RT": "&nbsp;",
    "EFG%": "&nbsp;",
    "O-RT": "&nbsp;",
    "PLAYER": "Sergio Rodriguez",
    "PLAYERID": "&nbsp;",
    "POS": "PG",
    "POW-AST": "33.16%",
    "POW-BLK": "3.77%",
    "POW-PTS": "9.56%",
    "POW-REB": "8.57%",
    "POW-STL": "12.50%",
    "SALARY": "-1",
    "TEAM": "PHI",
    "TS%": "&nbsp;",
    "USG%": "21.00%"
  },
  {
    "D-RT": "106",
    "EFG%": "50.59%",
    "O-RT": "97",
    "OPP": "HOU",
    "PLAYER": "Robert Covington",
    "PLAYERID": "16874",
    "POS": "SF",
    "POW-AST": "4.66%",
    "POW-BLK": "15.09%",
    "POW-PTS": "8.76%",
    "POW-REB": "11.17%",
    "POW-STL": "27.78%",
    "SALARY": "4800.00",
    "SCHEDULE_ID": "35456",
    "TEAM": "PHI",
    "TS%": "52.40%",
    "USG%": "15.06%"
  },
  {
    "D-RT": "&nbsp;",
    "EFG%": "&nbsp;",
    "O-RT": "&nbsp;",
    "PLAYER": "Dario Saric",
    "PLAYERID": "&nbsp;",
    "POS": "PF",
    "POW-AST": "8.29%",
    "POW-BLK": "3.77%",
    "POW-PTS": "9.91%",
    "POW-REB": "14.03%",
    "POW-STL": "8.33%",
    "SALARY": "-1",
    "TEAM": "PHI",
    "TS%": "&nbsp;",
    "USG%": "19.61%"
  },
  {
    "D-RT": "109",
    "EFG%": "47.33%",
    "O-RT": "104",
    "OPP": "HOU",
    "PLAYER": "Gerald Henderson",
    "PLAYERID": "1014",
    "POS": "SG",
    "POW-AST": "5.70%",
    "POW-BLK": "1.89%",
    "POW-PTS": "10.48%",
    "POW-REB": "7.01%",
    "POW-STL": "9.72%",
    "SALARY": "3900.00",
    "SCHEDULE_ID": "35456",
    "TEAM": "PHI",
    "TS%": "49.68%",
    "USG%": "18.10%"
  },
  {
    "D-RT": "106",
    "EFG%": "50.28%",
    "O-RT": "109",
    "OPP": "HOU",
    "PLAYER": "Ersan Ilyasova",
    "PLAYERID": "1301",
    "POS": "PF",
    "POW-AST": "5.70%",
    "POW-BLK": "5.66%",
    "POW-PTS": "10.25%",
    "POW-REB": "11.43%",
    "POW-STL": "6.94%",
    "SALARY": "3900.00",
    "SCHEDULE_ID": "35456",
    "TEAM": "PHI",
    "TS%": "51.31%",
    "USG%": "18.99%"
  },
  {
    "D-RT": "113",
    "EFG%": "57.64%",
    "O-RT": "98",
    "OPP": "HOU",
    "PLAYER": "Nik Stauskas",
    "PLAYERID": "18636",
    "POS": "SG",
    "POW-AST": "5.18%",
    "POW-BLK": "3.77%",
    "POW-PTS": "8.18%",
    "POW-REB": "5.97%",
    "POW-STL": "4.17%",
    "SALARY": "3600.00",
    "SCHEDULE_ID": "35456",
    "TEAM": "PHI",
    "TS%": "54.89%",
    "USG%": "14.64%"
  },
  {
    "D-RT": "&nbsp;",
    "EFG%": "54.67%",
    "O-RT": "&nbsp;",
    "PLAYER": "Joel Embiid",
    "PLAYERID": "&nbsp;",
    "POS": "C",
    "POW-AST": "4.15%",
    "POW-BLK": "26.42%",
    "POW-PTS": "13.02%",
    "POW-REB": "10.65%",
    "POW-STL": "4.17%",
    "SALARY": "-1",
    "TEAM": "PHI",
    "TS%": "57.71%",
    "USG%": "39.00%"
  },
  {
    "D-RT": "113",
    "EFG%": "39.08%",
    "O-RT": "101",
    "OPP": "HOU",
    "PLAYER": "Hollis Thompson",
    "PLAYERID": "16804",
    "POS": "SG",
    "POW-AST": "3.63%",
    "POW-BLK": "3.77%",
    "POW-PTS": "8.18%",
    "POW-REB": "9.35%",
    "POW-STL": "5.56%",
    "SALARY": "3700.00",
    "SCHEDULE_ID": "35456",
    "TEAM": "PHI",
    "TS%": "43.62%",
    "USG%": "15.52%"
  },
  {
    "D-RT": "108",
    "EFG%": "48.58%",
    "O-RT": "101",
    "OPP": "HOU",
    "PLAYER": "T.J. McConnell",
    "PLAYERID": "18956",
    "POS": "PG",
    "POW-AST": "22.28%",
    "POW-BLK": "0.00%",
    "POW-PTS": "4.03%",
    "POW-REB": "4.42%",
    "POW-STL": "12.50%",
    "SALARY": "3700.00",
    "SCHEDULE_ID": "35456",
    "TEAM": "PHI",
    "TS%": "50.74%",
    "USG%": "15.01%"
  },
  {
    "D-RT": "110",
    "EFG%": "45.83%",
    "O-RT": "99",
    "OPP": "HOU",
    "PLAYER": "Jahlil Okafor",
    "PLAYERID": "18902",
    "POS": "C",
    "POW-AST": "3.63%",
    "POW-BLK": "15.09%",
    "POW-PTS": "10.37%",
    "POW-REB": "8.05%",
    "POW-STL": "5.56%",
    "SALARY": "4800.00",
    "SCHEDULE_ID": "35456",
    "TEAM": "PHI",
    "TS%": "48.97%",
    "USG%": "27.33%"
  },
  {
    "D-RT": "108",
    "EFG%": "58.55%",
    "O-RT": "115",
    "OPP": "PHI",
    "PLAYER": "James Harden",
    "PLAYERID": "1037",
    "POS": "SG",
    "POW-AST": "53.67%",
    "POW-BLK": "0.00%",
    "POW-PTS": "28.04%",
    "POW-REB": "19.06%",
    "POW-STL": "15.38%",
    "SALARY": "11700.00",
    "SCHEDULE_ID": "35456",
    "TEAM": "HOU",
    "TS%": "62.21%",
    "USG%": "36.13%"
  },
  {
    "D-RT": "108",
    "EFG%": "50.82%",
    "O-RT": "110",
    "OPP": "PHI",
    "PLAYER": "Trevor Ariza",
    "PLAYERID": "1323",
    "POS": "SF",
    "POW-AST": "8.72%",
    "POW-BLK": "5.41%",
    "POW-PTS": "11.01%",
    "POW-REB": "10.18%",
    "POW-STL": "30.77%",
    "SALARY": "5000.00",
    "SCHEDULE_ID": "35456",
    "TEAM": "HOU",
    "TS%": "53.45%",
    "USG%": "14.40%"
  },
  {
    "D-RT": "112",
    "EFG%": "49.80%",
    "O-RT": "108",
    "OPP": "PHI",
    "PLAYER": "Ryan Anderson",
    "PLAYERID": "1281",
    "POS": "PF",
    "POW-AST": "2.29%",
    "POW-BLK": "0.00%",
    "POW-PTS": "12.67%",
    "POW-REB": "15.93%",
    "POW-STL": "6.15%",
    "SALARY": "5100.00",
    "SCHEDULE_ID": "35456",
    "TEAM": "HOU",
    "TS%": "51.43%",
    "USG%": "17.89%"
  },
  {
    "D-RT": "113",
    "EFG%": "48.14%",
    "O-RT": "108",
    "OPP": "PHI",
    "PLAYER": "Eric Gordon",
    "PLAYERID": "1077",
    "POS": "SG",
    "POW-AST": "8.72%",
    "POW-BLK": "16.22%",
    "POW-PTS": "15.58%",
    "POW-REB": "7.05%",
    "POW-STL": "10.77%",
    "SALARY": "5300.00",
    "SCHEDULE_ID": "35456",
    "TEAM": "HOU",
    "TS%": "52.82%",
    "USG%": "21.07%"
  },
  {
    "D-RT": "104",
    "EFG%": "12.50%",
    "O-RT": "114",
    "OPP": "PHI",
    "PLAYER": "Clint Capela",
    "PLAYERID": "18610",
    "POS": "C",
    "POW-AST": "2.29%",
    "POW-BLK": "29.73%",
    "POW-PTS": "9.35%",
    "POW-REB": "18.02%",
    "POW-STL": "7.69%",
    "SALARY": "4600.00",
    "SCHEDULE_ID": "35456",
    "TEAM": "HOU",
    "TS%": "12.50%",
    "USG%": "18.43%"
  },
  {
    "D-RT": "103",
    "EFG%": "55.93%",
    "O-RT": "106",
    "OPP": "PHI",
    "PLAYER": "Nene Hilario",
    "PLAYERID": "17321",
    "POS": "C",
    "POW-AST": "5.50%",
    "POW-BLK": "13.51%",
    "POW-PTS": "5.50%",
    "POW-REB": "7.31%",
    "POW-STL": "3.08%",
    "SALARY": "3500.00",
    "SCHEDULE_ID": "35456",
    "TEAM": "HOU",
    "TS%": "60.59%",
    "USG%": "14.15%"
  },
  {
    "D-RT": "109",
    "EFG%": "53.63%",
    "O-RT": "98",
    "OPP": "PHI",
    "PLAYER": "Corey Brewer",
    "PLAYERID": "1278",
    "POS": "SF",
    "POW-AST": "6.42%",
    "POW-BLK": "2.70%",
    "POW-PTS": "3.01%",
    "POW-REB": "3.92%",
    "POW-STL": "7.69%",
    "SALARY": "3500.00",
    "SCHEDULE_ID": "35456",
    "TEAM": "HOU",
    "TS%": "54.60%",
    "USG%": "13.77%"
  },
  {
    "D-RT": "110",
    "EFG%": "55.58%",
    "O-RT": "101",
    "OPP": "PHI",
    "PLAYER": "K.J. McDaniels",
    "PLAYERID": "18579",
    "POS": "SG",
    "POW-AST": "0.92%",
    "POW-BLK": "16.22%",
    "POW-PTS": "5.09%",
    "POW-REB": "3.39%",
    "POW-STL": "6.15%",
    "SALARY": "3500.00",
    "SCHEDULE_ID": "35456",
    "TEAM": "HOU",
    "TS%": "56.32%",
    "USG%": "13.66%"
  },
  {
    "D-RT": "95",
    "EFG%": "53.15%",
    "O-RT": "0",
    "OPP": "PHI",
    "PLAYER": "Sam Dekker",
    "PLAYERID": "18929",
    "POS": "SF",
    "POW-AST": "3.21%",
    "POW-BLK": "5.41%",
    "POW-PTS": "5.09%",
    "POW-REB": "8.36%",
    "POW-STL": "6.15%",
    "SALARY": "3500.00",
    "SCHEDULE_ID": "35456",
    "TEAM": "HOU",
    "TS%": "56.37%",
    "USG%": "15.25%"
  },
  {
    "D-RT": "110",
    "EFG%": "45.60%",
    "O-RT": "119",
    "OPP": "PHI",
    "PLAYER": "Montrezl Harrell",
    "PLAYERID": "18930",
    "POS": "PF",
    "POW-AST": "1.38%",
    "POW-BLK": "10.81%",
    "POW-PTS": "2.70%",
    "POW-REB": "3.92%",
    "POW-STL": "1.54%",
    "SALARY": "3500.00",
    "SCHEDULE_ID": "35456",
    "TEAM": "HOU",
    "TS%": "52.18%",
    "USG%": "19.43%"
  },
  {
    "D-RT": "105",
    "EFG%": "46.33%",
    "O-RT": "97",
    "OPP": "SAS",
    "PLAYER": "Justise Winslow",
    "PLAYERID": "18921",
    "POS": "SF",
    "POW-AST": "18.40%",
    "POW-BLK": "6.38%",
    "POW-PTS": "12.70%",
    "POW-REB": "11.02%",
    "POW-STL": "23.64%",
    "SALARY": "5000.00",
    "SCHEDULE_ID": "35457",
    "TEAM": "MIA",
    "TS%": "47.01%",
    "USG%": "20.62%"
  },
  {
    "D-RT": "95",
    "EFG%": "60.00%",
    "O-RT": "117",
    "OPP": "SAS",
    "PLAYER": "Hassan Whiteside",
    "PLAYERID": "18664",
    "POS": "C",
    "POW-AST": "3.68%",
    "POW-BLK": "42.55%",
    "POW-PTS": "18.32%",
    "POW-REB": "33.05%",
    "POW-STL": "10.91%",
    "SALARY": "8400.00",
    "SCHEDULE_ID": "35457",
    "TEAM": "MIA",
    "TS%": "59.52%",
    "USG%": "24.06%"
  },
  {
    "D-RT": "107",
    "EFG%": "50.20%",
    "O-RT": "105",
    "OPP": "SAS",
    "PLAYER": "Goran Dragic",
    "PLAYERID": "1040",
    "POS": "PG",
    "POW-AST": "25.15%",
    "POW-BLK": "4.26%",
    "POW-PTS": "14.92%",
    "POW-REB": "7.63%",
    "POW-STL": "12.73%",
    "SALARY": "6500.00",
    "SCHEDULE_ID": "35457",
    "TEAM": "MIA",
    "TS%": "55.67%",
    "USG%": "25.28%"
  },
  {
    "D-RT": "108",
    "EFG%": "48.61%",
    "O-RT": "99",
    "OPP": "SAS",
    "PLAYER": "Dion Waiters",
    "PLAYERID": "13897",
    "POS": "SG",
    "POW-AST": "17.79%",
    "POW-BLK": "8.51%",
    "POW-PTS": "10.08%",
    "POW-REB": "7.63%",
    "POW-STL": "10.91%",
    "SALARY": "4300.00",
    "SCHEDULE_ID": "35457",
    "TEAM": "MIA",
    "TS%": "54.58%",
    "USG%": "20.62%"
  },
  {
    "D-RT": "107",
    "EFG%": "53.79%",
    "O-RT": "111",
    "OPP": "SAS",
    "PLAYER": "Tyler Johnson",
    "PLAYERID": "18720",
    "POS": "PG",
    "POW-AST": "11.66%",
    "POW-BLK": "10.64%",
    "POW-PTS": "13.87%",
    "POW-REB": "9.89%",
    "POW-STL": "18.18%",
    "SALARY": "4900.00",
    "SCHEDULE_ID": "35457",
    "TEAM": "MIA",
    "TS%": "56.59%",
    "USG%": "17.75%"
  },
  {
    "D-RT": "106",
    "EFG%": "47.10%",
    "O-RT": "112",
    "OPP": "SAS",
    "PLAYER": "Josh Richardson",
    "PLAYERID": "18922",
    "POS": "SG",
    "POW-AST": "2.45%",
    "POW-BLK": "4.26%",
    "POW-PTS": "4.58%",
    "POW-REB": "2.54%",
    "POW-STL": "5.45%",
    "SALARY": "3800.00",
    "SCHEDULE_ID": "35457",
    "TEAM": "MIA",
    "TS%": "51.90%",
    "USG%": "19.30%"
  },
  {
    "D-RT": "106",
    "EFG%": "49.55%",
    "O-RT": "101",
    "OPP": "SAS",
    "PLAYER": "James Johnson",
    "PLAYERID": "1195",
    "POS": "SF",
    "POW-AST": "10.43%",
    "POW-BLK": "12.77%",
    "POW-PTS": "8.38%",
    "POW-REB": "9.60%",
    "POW-STL": "7.27%",
    "SALARY": "3800.00",
    "SCHEDULE_ID": "35457",
    "TEAM": "MIA",
    "TS%": "53.47%",
    "USG%": "17.39%"
  },
  {
    "D-RT": "112",
    "EFG%": "67.31%",
    "O-RT": "107",
    "OPP": "SAS",
    "PLAYER": "Luke Babbitt",
    "PLAYERID": "1226",
    "POS": "PF",
    "POW-AST": "3.68%",
    "POW-BLK": "0.00%",
    "POW-PTS": "6.15%",
    "POW-REB": "5.65%",
    "POW-STL": "3.64%",
    "SALARY": "3500.00",
    "SCHEDULE_ID": "35457",
    "TEAM": "MIA",
    "TS%": "66.34%",
    "USG%": "13.75%"
  },
  {
    "D-RT": "103",
    "EFG%": "50.54%",
    "O-RT": "99",
    "OPP": "SAS",
    "PLAYER": "Udonis Haslem",
    "PLAYERID": "1418",
    "POS": "PF",
    "POW-AST": "0.61%",
    "POW-BLK": "0.00%",
    "POW-PTS": "0.00%",
    "POW-REB": "1.13%",
    "POW-STL": "1.82%",
    "SALARY": "3500.00",
    "SCHEDULE_ID": "35457",
    "TEAM": "MIA",
    "TS%": "55.59%",
    "USG%": "8.88%"
  },
  {
    "D-RT": "&nbsp;",
    "EFG%": "52.54%",
    "O-RT": "&nbsp;",
    "PLAYER": "Rodney McGruder",
    "PLAYERID": "&nbsp;",
    "POS": "PG",
    "POW-AST": "3.07%",
    "POW-BLK": "2.13%",
    "POW-PTS": "4.58%",
    "POW-REB": "3.11%",
    "POW-STL": "3.64%",
    "SALARY": "-1",
    "TEAM": "MIA",
    "TS%": "54.21%",
    "USG%": "11.61%"
  },
  {
    "D-RT": "96",
    "EFG%": "51.17%",
    "O-RT": "121",
    "OPP": "MIA",
    "PLAYER": "Kawhi Leonard",
    "PLAYERID": "13310",
    "POS": "SF",
    "POW-AST": "12.32%",
    "POW-BLK": "8.47%",
    "POW-PTS": "25.12%",
    "POW-REB": "11.83%",
    "POW-STL": "30.86%",
    "SALARY": "8500.00",
    "SCHEDULE_ID": "35457",
    "TEAM": "SAS",
    "TS%": "56.25%",
    "USG%": "29.15%"
  },
  {
    "D-RT": "99",
    "EFG%": "49.79%",
    "O-RT": "114",
    "OPP": "MIA",
    "PLAYER": "LaMarcus Aldridge",
    "PLAYERID": "1349",
    "POS": "PF",
    "POW-AST": "4.74%",
    "POW-BLK": "13.56%",
    "POW-PTS": "15.41%",
    "POW-REB": "15.78%",
    "POW-STL": "6.17%",
    "SALARY": "7200.00",
    "SCHEDULE_ID": "35457",
    "TEAM": "SAS",
    "TS%": "54.97%",
    "USG%": "23.64%"
  },
  {
    "D-RT": "99",
    "EFG%": "49.68%",
    "O-RT": "99",
    "OPP": "MIA",
    "PLAYER": "Danny Green",
    "PLAYERID": "940",
    "POS": "SG",
    "POW-AST": "1.90%",
    "POW-BLK": "5.08%",
    "POW-PTS": "1.28%",
    "POW-REB": "0.70%",
    "POW-STL": "4.94%",
    "SALARY": "4300.00",
    "SCHEDULE_ID": "35457",
    "TEAM": "SAS",
    "TS%": "50.81%",
    "USG%": "12.32%"
  },
  {
    "D-RT": "103",
    "EFG%": "50.34%",
    "O-RT": "109",
    "OPP": "MIA",
    "PLAYER": "Tony Parker",
    "PLAYERID": "982",
    "POS": "PG",
    "POW-AST": "10.90%",
    "POW-BLK": "1.69%",
    "POW-PTS": "4.42%",
    "POW-REB": "2.55%",
    "POW-STL": "2.47%",
    "SALARY": "4300.00",
    "SCHEDULE_ID": "35457",
    "TEAM": "SAS",
    "TS%": "56.52%",
    "USG%": "16.81%"
  },
  {
    "D-RT": "101",
    "EFG%": "57.35%",
    "O-RT": "107",
    "OPP": "MIA",
    "PLAYER": "Pau Gasol",
    "PLAYERID": "1502",
    "POS": "C",
    "POW-AST": "13.27%",
    "POW-BLK": "22.03%",
    "POW-PTS": "10.11%",
    "POW-REB": "16.24%",
    "POW-STL": "3.70%",
    "SALARY": "6000.00",
    "SCHEDULE_ID": "35457",
    "TEAM": "SAS",
    "TS%": "56.97%",
    "USG%": "19.02%"
  },
  {
    "D-RT": "&nbsp;",
    "EFG%": "49.38%",
    "O-RT": "&nbsp;",
    "OPP": "MIA",
    "PLAYER": "Patty Mills",
    "PLAYERID": "13977",
    "POS": "PG",
    "POW-AST": "18.48%",
    "POW-BLK": "0.00%",
    "POW-PTS": "10.50%",
    "POW-REB": "4.41%",
    "POW-STL": "7.41%",
    "SALARY": "4200.00",
    "SCHEDULE_ID": "35457",
    "TEAM": "SAS",
    "TS%": "52.18%",
    "USG%": "18.59%"
  },
  {
    "D-RT": "102",
    "EFG%": "36.11%",
    "O-RT": "106",
    "OPP": "MIA",
    "PLAYER": "Jonathon Simmons",
    "PLAYERID": "31808",
    "POS": "SF",
    "POW-AST": "9.95%",
    "POW-BLK": "6.78%",
    "POW-PTS": "7.16%",
    "POW-REB": "6.96%",
    "POW-STL": "7.41%",
    "SALARY": "3500.00",
    "SCHEDULE_ID": "35457",
    "TEAM": "SAS",
    "TS%": "39.15%",
    "USG%": "16.59%"
  },
  {
    "D-RT": "97",
    "EFG%": "53.73%",
    "O-RT": "104",
    "OPP": "MIA",
    "PLAYER": "Kyle Anderson",
    "PLAYERID": "18615",
    "POS": "SF",
    "POW-AST": "5.21%",
    "POW-BLK": "5.08%",
    "POW-PTS": "2.65%",
    "POW-REB": "8.58%",
    "POW-STL": "12.35%",
    "SALARY": "3600.00",
    "SCHEDULE_ID": "35457",
    "TEAM": "SAS",
    "TS%": "56.10%",
    "USG%": "7.91%"
  },
  {
    "D-RT": "98",
    "EFG%": "48.44%",
    "O-RT": "107",
    "OPP": "MIA",
    "PLAYER": "Manu Ginobili",
    "PLAYERID": "965",
    "POS": "SG",
    "POW-AST": "9.48%",
    "POW-BLK": "3.39%",
    "POW-PTS": "7.46%",
    "POW-REB": "6.03%",
    "POW-STL": "8.64%",
    "SALARY": "3500.00",
    "SCHEDULE_ID": "35457",
    "TEAM": "SAS",
    "TS%": "51.42%",
    "USG%": "21.63%"
  },
  {
    "D-RT": "103",
    "EFG%": "58.28%",
    "O-RT": "111",
    "OPP": "MIA",
    "PLAYER": "David Lee",
    "PLAYERID": "1500",
    "POS": "PF",
    "POW-AST": "5.21%",
    "POW-BLK": "5.08%",
    "POW-PTS": "6.48%",
    "POW-REB": "10.67%",
    "POW-STL": "6.17%",
    "SALARY": "3500.00",
    "SCHEDULE_ID": "35457",
    "TEAM": "SAS",
    "TS%": "60.63%",
    "USG%": "14.82%"
  },
  {
    "D-RT": "106",
    "EFG%": "53.93%",
    "O-RT": "105",
    "OPP": "UTA",
    "PLAYER": "Marc Gasol",
    "PLAYERID": "1493",
    "POS": "C",
    "POW-AST": "16.48%",
    "POW-BLK": "27.66%",
    "POW-PTS": "16.61%",
    "POW-REB": "13.17%",
    "POW-STL": "6.10%",
    "SALARY": "7100.00",
    "SCHEDULE_ID": "35458",
    "TEAM": "MEM",
    "TS%": "57.45%",
    "USG%": "26.03%"
  },
  {
    "D-RT": "110",
    "EFG%": "43.63%",
    "O-RT": "115",
    "OPP": "UTA",
    "PLAYER": "Mike Conley",
    "PLAYERID": "1062",
    "POS": "PG",
    "POW-AST": "27.47%",
    "POW-BLK": "10.64%",
    "POW-PTS": "17.18%",
    "POW-REB": "6.72%",
    "POW-STL": "12.20%",
    "SALARY": "7000.00",
    "SCHEDULE_ID": "35458",
    "TEAM": "MEM",
    "TS%": "50.05%",
    "USG%": "26.91%"
  },
  {
    "D-RT": "110",
    "EFG%": "51.87%",
    "O-RT": "116",
    "OPP": "UTA",
    "PLAYER": "James Ennis",
    "PLAYERID": "18599",
    "POS": "SF",
    "POW-AST": "4.95%",
    "POW-BLK": "2.13%",
    "POW-PTS": "10.77%",
    "POW-REB": "14.78%",
    "POW-STL": "12.20%",
    "SALARY": "4300.00",
    "SCHEDULE_ID": "35458",
    "TEAM": "MEM",
    "TS%": "54.95%",
    "USG%": "13.44%"
  },
  {
    "D-RT": "107",
    "EFG%": "41.74%",
    "O-RT": "105",
    "OPP": "UTA",
    "PLAYER": "JaMychal Green",
    "PLAYERID": "18729",
    "POS": "PF",
    "POW-AST": "6.04%",
    "POW-BLK": "12.77%",
    "POW-PTS": "8.48%",
    "POW-REB": "11.83%",
    "POW-STL": "4.88%",
    "SALARY": "4000.00",
    "SCHEDULE_ID": "35458",
    "TEAM": "MEM",
    "TS%": "46.05%",
    "USG%": "14.25%"
  },
  {
    "D-RT": "108",
    "EFG%": "54.19%",
    "O-RT": "107",
    "OPP": "UTA",
    "PLAYER": "Vince Carter",
    "PLAYERID": "1066",
    "POS": "SF",
    "POW-AST": "9.34%",
    "POW-BLK": "12.77%",
    "POW-PTS": "9.62%",
    "POW-REB": "9.41%",
    "POW-STL": "9.76%",
    "SALARY": "4200.00",
    "SCHEDULE_ID": "35458",
    "TEAM": "MEM",
    "TS%": "59.11%",
    "USG%": "13.65%"
  },
  {
    "D-RT": "&nbsp;",
    "EFG%": "52.91%",
    "O-RT": "&nbsp;",
    "PLAYER": "Andrew Harrison",
    "PLAYERID": "&nbsp;",
    "POS": "PG",
    "POW-AST": "13.19%",
    "POW-BLK": "4.26%",
    "POW-PTS": "5.27%",
    "POW-REB": "2.96%",
    "POW-STL": "14.63%",
    "SALARY": "-1",
    "TEAM": "MEM",
    "TS%": "54.95%",
    "USG%": "16.31%"
  },
  {
    "D-RT": "105",
    "EFG%": "50.45%",
    "O-RT": "101",
    "OPP": "UTA",
    "PLAYER": "Tony Allen",
    "PLAYERID": "1284",
    "POS": "SG",
    "POW-AST": "1.10%",
    "POW-BLK": "0.00%",
    "POW-PTS": "2.63%",
    "POW-REB": "4.84%",
    "POW-STL": "9.76%",
    "SALARY": "4000.00",
    "SCHEDULE_ID": "35458",
    "TEAM": "MEM",
    "TS%": "53.22%",
    "USG%": "17.03%"
  },
  {
    "D-RT": "108",
    "EFG%": "51.05%",
    "O-RT": "110",
    "OPP": "UTA",
    "PLAYER": "Chandler Parsons",
    "PLAYERID": "13319",
    "POS": "SF",
    "POW-AST": "1.65%",
    "POW-BLK": "4.26%",
    "POW-PTS": "2.41%",
    "POW-REB": "2.69%",
    "POW-STL": "2.44%",
    "SALARY": "5300.00",
    "SCHEDULE_ID": "35458",
    "TEAM": "MEM",
    "TS%": "53.10%",
    "USG%": "20.89%"
  },
  {
    "D-RT": "109",
    "EFG%": "52.23%",
    "O-RT": "107",
    "OPP": "UTA",
    "PLAYER": "Zach Randolph",
    "PLAYERID": "1668",
    "POS": "PF",
    "POW-AST": "4.95%",
    "POW-BLK": "0.00%",
    "POW-PTS": "14.20%",
    "POW-REB": "19.09%",
    "POW-STL": "7.32%",
    "SALARY": "5400.00",
    "SCHEDULE_ID": "35458",
    "TEAM": "MEM",
    "TS%": "56.25%",
    "USG%": "29.64%"
  },
  {
    "D-RT": "&nbsp;",
    "EFG%": "&nbsp;",
    "O-RT": "&nbsp;",
    "PLAYER": "Wade Baldwin",
    "PLAYERID": "&nbsp;",
    "POS": "SG",
    "POW-AST": "12.09%",
    "POW-BLK": "6.38%",
    "POW-PTS": "3.21%",
    "POW-REB": "4.30%",
    "POW-STL": "9.76%",
    "SALARY": "-1",
    "TEAM": "MEM",
    "TS%": "&nbsp;",
    "USG%": "17.92%"
  },
  {
    "D-RT": "105",
    "EFG%": "63.89%",
    "O-RT": "110",
    "OPP": "MEM",
    "PLAYER": "Gordon Hayward",
    "PLAYERID": "1239",
    "POS": "SF",
    "POW-AST": "10.40%",
    "POW-BLK": "1.61%",
    "POW-PTS": "11.36%",
    "POW-REB": "8.17%",
    "POW-STL": "4.05%",
    "SALARY": "7700.00",
    "SCHEDULE_ID": "35458",
    "TEAM": "UTA",
    "TS%": "65.08%",
    "USG%": "28.38%"
  },
  {
    "D-RT": "106",
    "EFG%": "50.68%",
    "O-RT": "112",
    "OPP": "MEM",
    "PLAYER": "George Hill",
    "PLAYERID": "993",
    "POS": "PG",
    "POW-AST": "17.33%",
    "POW-BLK": "3.23%",
    "POW-PTS": "13.31%",
    "POW-REB": "4.30%",
    "POW-STL": "9.46%",
    "SALARY": "6300.00",
    "SCHEDULE_ID": "35458",
    "TEAM": "UTA",
    "TS%": "54.03%",
    "USG%": "22.09%"
  },
  {
    "D-RT": "107",
    "EFG%": "42.29%",
    "O-RT": "109",
    "OPP": "MEM",
    "PLAYER": "Rodney Hood",
    "PLAYERID": "18629",
    "POS": "SG",
    "POW-AST": "10.40%",
    "POW-BLK": "6.45%",
    "POW-PTS": "17.78%",
    "POW-REB": "10.32%",
    "POW-STL": "13.51%",
    "SALARY": "5300.00",
    "SCHEDULE_ID": "35458",
    "TEAM": "UTA",
    "TS%": "45.97%",
    "USG%": "20.95%"
  },
  {
    "D-RT": "99",
    "EFG%": "61.27%",
    "O-RT": "112",
    "OPP": "MEM",
    "PLAYER": "Rudy Gobert",
    "PLAYERID": "16935",
    "POS": "C",
    "POW-AST": "5.94%",
    "POW-BLK": "40.32%",
    "POW-PTS": "10.15%",
    "POW-REB": "25.38%",
    "POW-STL": "10.81%",
    "SALARY": "6600.00",
    "SCHEDULE_ID": "35458",
    "TEAM": "UTA",
    "TS%": "62.29%",
    "USG%": "13.27%"
  },
  {
    "D-RT": "113",
    "EFG%": "48.50%",
    "O-RT": "104",
    "OPP": "MEM",
    "PLAYER": "Joe Johnson",
    "PLAYERID": "1082",
    "POS": "SF",
    "POW-AST": "12.87%",
    "POW-BLK": "1.61%",
    "POW-PTS": "10.71%",
    "POW-REB": "8.17%",
    "POW-STL": "9.46%",
    "SALARY": "3900.00",
    "SCHEDULE_ID": "35458",
    "TEAM": "UTA",
    "TS%": "52.86%",
    "USG%": "16.37%"
  },
  {
    "D-RT": "101",
    "EFG%": "55.51%",
    "O-RT": "111",
    "OPP": "MEM",
    "PLAYER": "Derrick Favors",
    "PLAYERID": "1266",
    "POS": "PF",
    "POW-AST": "2.97%",
    "POW-BLK": "17.74%",
    "POW-PTS": "10.15%",
    "POW-REB": "15.27%",
    "POW-STL": "12.16%",
    "SALARY": "6800.00",
    "SCHEDULE_ID": "35458",
    "TEAM": "UTA",
    "TS%": "58.90%",
    "USG%": "20.49%"
  },
  {
    "D-RT": "102",
    "EFG%": "60.22%",
    "O-RT": "109",
    "OPP": "MEM",
    "PLAYER": "Boris Diaw",
    "PLAYERID": "1312",
    "POS": "PF",
    "POW-AST": "0.99%",
    "POW-BLK": "0.00%",
    "POW-PTS": "0.19%",
    "POW-REB": "1.51%",
    "POW-STL": "0.00%",
    "SALARY": "3500.00",
    "SCHEDULE_ID": "35458",
    "TEAM": "UTA",
    "TS%": "60.92%",
    "USG%": "10.39%"
  },
  {
    "D-RT": "105",
    "EFG%": "49.67%",
    "O-RT": "102",
    "OPP": "MEM",
    "PLAYER": "Trey Lyles",
    "PLAYERID": "18942",
    "POS": "PF",
    "POW-AST": "7.92%",
    "POW-BLK": "9.68%",
    "POW-PTS": "6.80%",
    "POW-REB": "9.68%",
    "POW-STL": "5.41%",
    "SALARY": "3600.00",
    "SCHEDULE_ID": "35458",
    "TEAM": "UTA",
    "TS%": "52.49%",
    "USG%": "17.54%"
  },
  {
    "D-RT": "&nbsp;",
    "EFG%": "47.60%",
    "O-RT": "&nbsp;",
    "PLAYER": "Dante Exum",
    "PLAYERID": "&nbsp;",
    "POS": "PG",
    "POW-AST": "8.91%",
    "POW-BLK": "8.06%",
    "POW-PTS": "6.61%",
    "POW-REB": "5.59%",
    "POW-STL": "2.70%",
    "SALARY": "-1",
    "TEAM": "UTA",
    "TS%": "51.35%",
    "USG%": "15.02%"
  },
  {
    "D-RT": "106",
    "EFG%": "57.14%",
    "O-RT": "99",
    "OPP": "MEM",
    "PLAYER": "Shelvin Mack",
    "PLAYERID": "13354",
    "POS": "PG",
    "POW-AST": "13.37%",
    "POW-BLK": "0.00%",
    "POW-PTS": "7.54%",
    "POW-REB": "4.95%",
    "POW-STL": "14.86%",
    "SALARY": "3900.00",
    "SCHEDULE_ID": "35458",
    "TEAM": "UTA",
    "TS%": "58.87%",
    "USG%": "21.01%"
  },
  {
    "D-RT": "115",
    "EFG%": "51.74%",
    "O-RT": "102",
    "OPP": "LAC",
    "PLAYER": "Bojan Bogdanovic",
    "PLAYERID": "18571",
    "POS": "SF",
    "POW-AST": "6.42%",
    "POW-BLK": "2.44%",
    "POW-PTS": "12.23%",
    "POW-REB": "7.93%",
    "POW-STL": "6.25%",
    "SALARY": "4000.00",
    "SCHEDULE_ID": "35459",
    "TEAM": "BKN",
    "TS%": "53.30%",
    "USG%": "19.89%"
  },
  {
    "D-RT": "115",
    "EFG%": "50.10%",
    "O-RT": "110",
    "OPP": "LAC",
    "PLAYER": "Sean Kilpatrick",
    "PLAYERID": "18781",
    "POS": "SG",
    "POW-AST": "12.83%",
    "POW-BLK": "2.44%",
    "POW-PTS": "14.84%",
    "POW-REB": "10.34%",
    "POW-STL": "11.25%",
    "SALARY": "5500.00",
    "SCHEDULE_ID": "35459",
    "TEAM": "BKN",
    "TS%": "54.12%",
    "USG%": "26.05%"
  },
  {
    "D-RT": "105",
    "EFG%": "48.40%",
    "O-RT": "107",
    "OPP": "LAC",
    "PLAYER": "Rondae Hollis-Jefferson",
    "PLAYERID": "18897",
    "POS": "SF",
    "POW-AST": "14.97%",
    "POW-BLK": "9.76%",
    "POW-PTS": "6.58%",
    "POW-REB": "11.30%",
    "POW-STL": "11.25%",
    "SALARY": "4300.00",
    "SCHEDULE_ID": "35459",
    "TEAM": "BKN",
    "TS%": "51.00%",
    "USG%": "14.51%"
  },
  {
    "D-RT": "102",
    "EFG%": "46.66%",
    "O-RT": "109",
    "OPP": "LAC",
    "PLAYER": "Trevor Booker",
    "PLAYERID": "1147",
    "POS": "PF",
    "POW-AST": "9.63%",
    "POW-BLK": "17.07%",
    "POW-PTS": "9.61%",
    "POW-REB": "19.23%",
    "POW-STL": "22.50%",
    "SALARY": "5600.00",
    "SCHEDULE_ID": "35459",
    "TEAM": "BKN",
    "TS%": "51.02%",
    "USG%": "16.47%"
  },
  {
    "D-RT": "106",
    "EFG%": "46.42%",
    "O-RT": "102",
    "OPP": "LAC",
    "PLAYER": "Jeremy Lin",
    "PLAYERID": "916",
    "POS": "PG",
    "POW-AST": "16.04%",
    "POW-BLK": "4.88%",
    "POW-PTS": "7.84%",
    "POW-REB": "4.57%",
    "POW-STL": "8.75%",
    "SALARY": "6300.00",
    "SCHEDULE_ID": "35459",
    "TEAM": "BKN",
    "TS%": "53.68%",
    "USG%": "27.35%"
  },
  {
    "D-RT": "109",
    "EFG%": "54.81%",
    "O-RT": "109",
    "OPP": "LAC",
    "PLAYER": "Brook Lopez",
    "PLAYERID": "1498",
    "POS": "C",
    "POW-AST": "4.28%",
    "POW-BLK": "31.71%",
    "POW-PTS": "16.20%",
    "POW-REB": "9.13%",
    "POW-STL": "3.75%",
    "SALARY": "6800.00",
    "SCHEDULE_ID": "35459",
    "TEAM": "BKN",
    "TS%": "61.92%",
    "USG%": "30.72%"
  },
  {
    "D-RT": "&nbsp;",
    "EFG%": "50.06%",
    "O-RT": "&nbsp;",
    "PLAYER": "Justin Hamilton",
    "PLAYERID": "&nbsp;",
    "POS": "C",
    "POW-AST": "4.28%",
    "POW-BLK": "14.63%",
    "POW-PTS": "8.88%",
    "POW-REB": "11.30%",
    "POW-STL": "10.00%",
    "SALARY": "-1",
    "TEAM": "BKN",
    "TS%": "53.38%",
    "USG%": "14.04%"
  },
  {
    "D-RT": "107",
    "EFG%": "54.43%",
    "O-RT": "81",
    "OPP": "LAC",
    "PLAYER": "Joe Harris",
    "PLAYERID": "18587",
    "POS": "SG",
    "POW-AST": "5.88%",
    "POW-BLK": "4.88%",
    "POW-PTS": "9.09%",
    "POW-REB": "6.25%",
    "POW-STL": "8.75%",
    "SALARY": "3600.00",
    "SCHEDULE_ID": "35459",
    "TEAM": "BKN",
    "TS%": "56.40%",
    "USG%": "18.50%"
  },
  {
    "D-RT": "&nbsp;",
    "EFG%": "34.21%",
    "O-RT": "&nbsp;",
    "PLAYER": "Isaiah Whitehead",
    "PLAYERID": "&nbsp;",
    "POS": "PG",
    "POW-AST": "9.63%",
    "POW-BLK": "4.88%",
    "POW-PTS": "2.93%",
    "POW-REB": "4.33%",
    "POW-STL": "3.75%",
    "SALARY": "-1",
    "TEAM": "BKN",
    "TS%": "37.07%",
    "USG%": "22.51%"
  },
  {
    "D-RT": "105",
    "EFG%": "55.13%",
    "O-RT": "105",
    "OPP": "LAC",
    "PLAYER": "Luis Scola",
    "PLAYERID": "1331",
    "POS": "PF",
    "POW-AST": "6.95%",
    "POW-BLK": "2.44%",
    "POW-PTS": "6.27%",
    "POW-REB": "11.06%",
    "POW-STL": "6.25%",
    "SALARY": "3700.00",
    "SCHEDULE_ID": "35459",
    "TEAM": "BKN",
    "TS%": "57.30%",
    "USG%": "19.35%"
  },
  {
    "D-RT": "103",
    "EFG%": "70.04%",
    "O-RT": "108",
    "OPP": "BKN",
    "PLAYER": "Blake Griffin",
    "PLAYERID": "1503",
    "POS": "PF",
    "POW-AST": "18.57%",
    "POW-BLK": "10.00%",
    "POW-PTS": "18.88%",
    "POW-REB": "21.35%",
    "POW-STL": "12.37%",
    "SALARY": "8700.00",
    "SCHEDULE_ID": "35459",
    "TEAM": "LAC",
    "TS%": "62.33%",
    "USG%": "27.54%"
  },
  {
    "D-RT": "98",
    "EFG%": "56.39%",
    "O-RT": "122",
    "OPP": "BKN",
    "PLAYER": "DeAndre Jordan",
    "PLAYERID": "1486",
    "POS": "C",
    "POW-AST": "3.33%",
    "POW-BLK": "38.00%",
    "POW-PTS": "10.09%",
    "POW-REB": "26.58%",
    "POW-STL": "4.12%",
    "SALARY": "6900.00",
    "SCHEDULE_ID": "35459",
    "TEAM": "LAC",
    "TS%": "58.93%",
    "USG%": "15.57%"
  },
  {
    "D-RT": "103",
    "EFG%": "62.09%",
    "O-RT": "119",
    "OPP": "BKN",
    "PLAYER": "Chris Paul",
    "PLAYERID": "1087",
    "POS": "PG",
    "POW-AST": "40.48%",
    "POW-BLK": "6.00%",
    "POW-PTS": "17.76%",
    "POW-REB": "12.20%",
    "POW-STL": "27.84%",
    "SALARY": "9200.00",
    "SCHEDULE_ID": "35459",
    "TEAM": "LAC",
    "TS%": "66.15%",
    "USG%": "26.59%"
  },
  {
    "D-RT": "109",
    "EFG%": "48.25%",
    "O-RT": "118",
    "OPP": "BKN",
    "PLAYER": "J.J. Redick",
    "PLAYERID": "1030",
    "POS": "SG",
    "POW-AST": "3.33%",
    "POW-BLK": "0.00%",
    "POW-PTS": "11.96%",
    "POW-REB": "4.14%",
    "POW-STL": "10.31%",
    "SALARY": "4100.00",
    "SCHEDULE_ID": "35459",
    "TEAM": "LAC",
    "TS%": "51.15%",
    "USG%": "19.33%"
  },
  {
    "D-RT": "&nbsp;",
    "EFG%": "50.34%",
    "O-RT": "&nbsp;",
    "OPP": "BKN",
    "PLAYER": "Luc Richard Mbah a Moute",
    "PLAYERID": "14026",
    "POS": "SF",
    "POW-AST": "1.43%",
    "POW-BLK": "10.00%",
    "POW-PTS": "5.05%",
    "POW-REB": "5.45%",
    "POW-STL": "12.37%",
    "SALARY": "3700.00",
    "SCHEDULE_ID": "35459",
    "TEAM": "LAC",
    "TS%": "55.00%",
    "USG%": "9.42%"
  },
  {
    "D-RT": "107",
    "EFG%": "45.33%",
    "O-RT": "101",
    "OPP": "BKN",
    "PLAYER": "Austin Rivers",
    "PLAYERID": "13903",
    "POS": "PG",
    "POW-AST": "9.05%",
    "POW-BLK": "4.00%",
    "POW-PTS": "7.66%",
    "POW-REB": "3.70%",
    "POW-STL": "5.15%",
    "SALARY": "3600.00",
    "SCHEDULE_ID": "35459",
    "TEAM": "LAC",
    "TS%": "51.73%",
    "USG%": "19.00%"
  },
  {
    "D-RT": "109",
    "EFG%": "52.46%",
    "O-RT": "104",
    "OPP": "BKN",
    "PLAYER": "Jamal Crawford",
    "PLAYERID": "1075",
    "POS": "SG",
    "POW-AST": "10.00%",
    "POW-BLK": "2.00%",
    "POW-PTS": "9.91%",
    "POW-REB": "3.92%",
    "POW-STL": "12.37%",
    "SALARY": "4100.00",
    "SCHEDULE_ID": "35459",
    "TEAM": "LAC",
    "TS%": "57.93%",
    "USG%": "21.79%"
  },
  {
    "D-RT": "108",
    "EFG%": "51.57%",
    "O-RT": "102",
    "OPP": "BKN",
    "PLAYER": "Raymond Felton",
    "PLAYERID": "1078",
    "POS": "PG",
    "POW-AST": "7.62%",
    "POW-BLK": "8.00%",
    "POW-PTS": "4.77%",
    "POW-REB": "3.27%",
    "POW-STL": "8.25%",
    "SALARY": "3500.00",
    "SCHEDULE_ID": "35459",
    "TEAM": "LAC",
    "TS%": "53.16%",
    "USG%": "13.70%"
  },
  {
    "D-RT": "102",
    "EFG%": "51.45%",
    "O-RT": "98",
    "OPP": "BKN",
    "PLAYER": "Wesley Johnson",
    "PLAYERID": "1280",
    "POS": "SF",
    "POW-AST": "1.43%",
    "POW-BLK": "14.00%",
    "POW-PTS": "2.71%",
    "POW-REB": "7.41%",
    "POW-STL": "4.12%",
    "SALARY": "3500.00",
    "SCHEDULE_ID": "35459",
    "TEAM": "LAC",
    "TS%": "55.02%",
    "USG%": "13.26%"
  },
  {
    "D-RT": "103",
    "EFG%": "50.81%",
    "O-RT": "102",
    "OPP": "BKN",
    "PLAYER": "Marreese Speights",
    "PLAYERID": "1235",
    "POS": "PF",
    "POW-AST": "3.33%",
    "POW-BLK": "6.00%",
    "POW-PTS": "8.97%",
    "POW-REB": "9.37%",
    "POW-STL": "2.06%",
    "SALARY": "3600.00",
    "SCHEDULE_ID": "35459",
    "TEAM": "LAC",
    "TS%": "50.81%",
    "USG%": "24.83%"
  }
]