[
  {
    "3pa": 3,
    "3pm": 0,
    "abbr": "BOS",
    "ast": 2,
    "blk": 1,
    "fga": 12,
    "fgm": 4,
    "fpts": "27.12",
    "fta": 0,
    "ftm": 0,
    "gp": 1,
    "min": 48,
    "pace": 11,
    "pts": 9,
    "reb": 9,
    "stl": 0,
    "team": "Boston Celtics",
    "to": 0,
    "usg": "10.55"
  },
  {
    "3pa": 10,
    "3pm": 4,
    "abbr": "BKN",
    "ast": 3,
    "blk": 1,
    "fga": 22,
    "fgm": 11,
    "fpts": "48.91",
    "fta": 6,
    "ftm": 3,
    "gp": 1,
    "min": 48,
    "pace": 27,
    "pts": 31,
    "reb": 7,
    "stl": 0,
    "team": "Brooklyn Nets",
    "to": 3,
    "usg": "23.86"
  },
  {
    "3pa": 5,
    "3pm": 2,
    "abbr": "NYK",
    "ast": 3,
    "blk": 2,
    "fga": 18,
    "fgm": 10,
    "fpts": "59.53",
    "fta": 4,
    "ftm": 3,
    "gp": 1,
    "min": 48,
    "pace": 20,
    "pts": 27,
    "reb": 16,
    "stl": 3,
    "team": "New York Knicks",
    "to": 4,
    "usg": "20.63"
  },
  {
    "3pa": 0,
    "3pm": 0,
    "abbr": "PHI",
    "ast": 2,
    "blk": 4,
    "fga": 22,
    "fgm": 14,
    "fpts": "50.30",
    "fta": 10,
    "ftm": 2,
    "gp": 1,
    "min": 48,
    "pace": 29,
    "pts": 31,
    "reb": 6,
    "stl": 2,
    "team": "Philadelphia 76ers",
    "to": 4,
    "usg": "25.88"
  },
  {
    "3pa": 0,
    "3pm": 0,
    "abbr": "TOR",
    "ast": 1,
    "blk": 3,
    "fga": 9,
    "fgm": 7,
    "fpts": "36.05",
    "fta": 0,
    "ftm": 0,
    "gp": 1,
    "min": 48,
    "pace": 6,
    "pts": 14,
    "reb": 9,
    "stl": 2,
    "team": "Toronto Raptors",
    "to": 1,
    "usg": "8.61"
  },
  {
    "3pa": 0,
    "3pm": 0,
    "abbr": "CHI",
    "ast": 1,
    "blk": 0,
    "fga": 6,
    "fgm": 4,
    "fpts": "22.35",
    "fta": 0,
    "ftm": 0,
    "gp": 1,
    "min": 48,
    "pace": 5,
    "pts": 9,
    "reb": 8,
    "stl": 0,
    "team": "Chicago Bulls",
    "to": 0,
    "usg": "5.28"
  },
  {
    "3pa": 0,
    "3pm": 0,
    "abbr": "DET",
    "ast": 5,
    "blk": 1,
    "fga": 17,
    "fgm": 9,
    "fpts": "58.70",
    "fta": 8,
    "ftm": 5,
    "gp": 1,
    "min": 48,
    "pace": 18,
    "pts": 24,
    "reb": 19,
    "stl": 1,
    "team": "Detroit Pistons",
    "to": 2,
    "usg": "20.14"
  },
  {
    "3pa": 0,
    "3pm": 0,
    "abbr": "IND",
    "ast": 0,
    "blk": 2,
    "fga": 20,
    "fgm": 13,
    "fpts": "54.92",
    "fta": 1,
    "ftm": 1,
    "gp": 1,
    "min": 48,
    "pace": 20.5,
    "pts": 30,
    "reb": 13,
    "stl": 1,
    "team": "Indiana Pacers",
    "to": 2,
    "usg": "18.70"
  },
  {
    "3pa": 0,
    "3pm": 0,
    "abbr": "ATL",
    "ast": 0,
    "blk": 3,
    "fga": 10,
    "fgm": 6,
    "fpts": "48.65",
    "fta": 12,
    "ftm": 8,
    "gp": 1,
    "min": 48,
    "pace": 12,
    "pts": 21,
    "reb": 14,
    "stl": 3,
    "team": "Atlanta Hawks",
    "to": 3,
    "usg": "15.23"
  },
  {
    "3pa": 1,
    "3pm": 0,
    "abbr": "CHA",
    "ast": 5,
    "blk": 2,
    "fga": 15,
    "fgm": 9,
    "fpts": "46.58",
    "fta": 12,
    "ftm": 5,
    "gp": 1,
    "min": 48,
    "pace": 21,
    "pts": 25,
    "reb": 6,
    "stl": 1,
    "team": "Charlotte Hornets",
    "to": 1,
    "usg": "19.11"
  },
  {
    "3pa": 0,
    "3pm": 0,
    "abbr": "ORL",
    "ast": 6,
    "blk": 1,
    "fga": 18,
    "fgm": 9,
    "fpts": "57.27",
    "fta": 7,
    "ftm": 3,
    "gp": 1,
    "min": 48,
    "pace": 14.5,
    "pts": 23,
    "reb": 17,
    "stl": 0,
    "team": "Orlando Magic",
    "to": 0,
    "usg": "19.22"
  },
  {
    "3pa": 0,
    "3pm": 0,
    "abbr": "WAS",
    "ast": 4,
    "blk": 2,
    "fga": 13,
    "fgm": 8,
    "fpts": "44.73",
    "fta": 2,
    "ftm": 1,
    "gp": 1,
    "min": 48,
    "pace": 11,
    "pts": 17,
    "reb": 14,
    "stl": 1,
    "team": "Washington Wizards",
    "to": 2,
    "usg": "14.33"
  },
  {
    "3pa": 2,
    "3pm": 2,
    "abbr": "DAL",
    "ast": 0,
    "blk": 0,
    "fga": 16,
    "fgm": 12,
    "fpts": "56.64",
    "fta": 7,
    "ftm": 7,
    "gp": 1,
    "min": 48,
    "pace": 15.5,
    "pts": 33,
    "reb": 19,
    "stl": 0,
    "team": "Dallas Mavericks",
    "to": 0,
    "usg": "15.90"
  },
  {
    "3pa": 0,
    "3pm": 0,
    "abbr": "HOU",
    "ast": 2,
    "blk": 2,
    "fga": 6,
    "fgm": 4,
    "fpts": "18.06",
    "fta": 0,
    "ftm": 0,
    "gp": 1,
    "min": 48,
    "pace": 10,
    "pts": 9,
    "reb": 4,
    "stl": 0,
    "team": "Houston Rockets",
    "to": 4,
    "usg": "8.88"
  },
  {
    "3pa": 0,
    "3pm": 0,
    "abbr": "SAS",
    "ast": 0,
    "blk": 0,
    "fga": 0,
    "fgm": 0,
    "fpts": "12.00",
    "fta": 24,
    "ftm": 12,
    "gp": 1,
    "min": 48,
    "pace": 12,
    "pts": 12,
    "reb": 0,
    "stl": 0,
    "team": "San Antonio Spurs",
    "to": 0,
    "usg": "8.80"
  },
  {
    "3pa": 0,
    "3pm": 0,
    "abbr": "MIN",
    "ast": 9,
    "blk": 2,
    "fga": 11,
    "fgm": 6,
    "fpts": "52.90",
    "fta": 0,
    "ftm": 0,
    "gp": 1,
    "min": 48,
    "pace": 9,
    "pts": 12,
    "reb": 16,
    "stl": 2,
    "team": "Minnesota Timberwolves",
    "to": 2,
    "usg": "13.31"
  },
  {
    "3pa": 4,
    "3pm": 0,
    "abbr": "POR",
    "ast": 2,
    "blk": 2,
    "fga": 18,
    "fgm": 6,
    "fpts": "40.00",
    "fta": 0,
    "ftm": 0,
    "gp": 1,
    "min": 48,
    "pace": 23,
    "pts": 13,
    "reb": 22,
    "stl": 0,
    "team": "Portland Trail Blazers",
    "to": 9,
    "usg": "23.05"
  },
  {
    "3pa": 1,
    "3pm": 0,
    "abbr": "OKC",
    "ast": 3,
    "blk": 0,
    "fga": 8,
    "fgm": 5,
    "fpts": "33.66",
    "fta": 6,
    "ftm": 6,
    "gp": 1,
    "min": 48,
    "pace": 10,
    "pts": 17,
    "reb": 7,
    "stl": 1,
    "team": "Oklahoma City Thunder",
    "to": 2,
    "usg": "11.36"
  },
  {
    "3pa": 0,
    "3pm": 0,
    "abbr": "UTA",
    "ast": 1,
    "blk": 4,
    "fga": 5,
    "fgm": 2,
    "fpts": "38.84",
    "fta": 5,
    "ftm": 4,
    "gp": 1,
    "min": 48,
    "pace": 4.5,
    "pts": 10,
    "reb": 16,
    "stl": 1,
    "team": "Utah Jazz",
    "to": 4,
    "usg": "9.61"
  },
  {
    "3pa": 0,
    "3pm": 0,
    "abbr": "GSW",
    "ast": 11,
    "blk": 0,
    "fga": 11,
    "fgm": 8,
    "fpts": "48.00",
    "fta": 5,
    "ftm": 0,
    "gp": 1,
    "min": 48,
    "pace": 13.5,
    "pts": 16,
    "reb": 14,
    "stl": 0,
    "team": "Golden State Warriors",
    "to": 2,
    "usg": "15.69"
  },
  {
    "3pa": 0,
    "3pm": 0,
    "abbr": "LAC",
    "ast": 2,
    "blk": 6,
    "fga": 18,
    "fgm": 12,
    "fpts": "69.50",
    "fta": 16,
    "ftm": 8,
    "gp": 1,
    "min": 48,
    "pace": 22,
    "pts": 33,
    "reb": 18,
    "stl": 0,
    "team": "Los Angeles Clippers",
    "to": 2,
    "usg": "23.08"
  },
  {
    "3pa": 0,
    "3pm": 0,
    "abbr": "PHO",
    "ast": 0,
    "blk": 1,
    "fga": 12,
    "fgm": 9,
    "fpts": "52.93",
    "fta": 7,
    "ftm": 2,
    "gp": 1,
    "min": 48,
    "pace": 14.5,
    "pts": 20,
    "reb": 18,
    "stl": 3,
    "team": "Phoenix Suns",
    "to": 0,
    "usg": "12.57"
  }
]