[
  {
    "3pa": 83,
    "3pm": 27,
    "abbr": "BOS",
    "ast": 54,
    "blk": 13,
    "fga": 249,
    "fgm": 108,
    "fpts": "583.40",
    "fta": 58,
    "ftm": 44,
    "gp": 14,
    "min": 672,
    "pace": 273,
    "pts": 288,
    "reb": 159,
    "stl": 19,
    "team": "Boston Celtics",
    "to": 42,
    "usg": "19.90"
  },
  {
    "3pa": 80,
    "3pm": 23,
    "abbr": "BKN",
    "ast": 30,
    "blk": 24,
    "fga": 233,
    "fgm": 99,
    "fpts": "585.76",
    "fta": 69,
    "ftm": 49,
    "gp": 14,
    "min": 672,
    "pace": 270.5,
    "pts": 272,
    "reb": 166,
    "stl": 28,
    "team": "Brooklyn Nets",
    "to": 38,
    "usg": "18.53"
  },
  {
    "3pa": 78,
    "3pm": 29,
    "abbr": "NYK",
    "ast": 44,
    "blk": 16,
    "fga": 265,
    "fgm": 133,
    "fpts": "643.04",
    "fta": 81,
    "ftm": 58,
    "gp": 14,
    "min": 672,
    "pace": 289.5,
    "pts": 355,
    "reb": 148,
    "stl": 21,
    "team": "New York Knicks",
    "to": 33,
    "usg": "20.72"
  },
  {
    "3pa": 52,
    "3pm": 19,
    "abbr": "PHI",
    "ast": 33,
    "blk": 17,
    "fga": 198,
    "fgm": 82,
    "fpts": "471.34",
    "fta": 52,
    "ftm": 38,
    "gp": 11,
    "min": 528,
    "pace": 214,
    "pts": 222,
    "reb": 143,
    "stl": 11,
    "team": "Philadelphia 76ers",
    "to": 31,
    "usg": "19.91"
  },
  {
    "3pa": 43,
    "3pm": 18,
    "abbr": "TOR",
    "ast": 43,
    "blk": 13,
    "fga": 226,
    "fgm": 106,
    "fpts": "575.08",
    "fta": 56,
    "ftm": 45,
    "gp": 13,
    "min": 624,
    "pace": 229,
    "pts": 278,
    "reb": 178,
    "stl": 10,
    "team": "Toronto Raptors",
    "to": 31,
    "usg": "18.96"
  },
  {
    "3pa": 46,
    "3pm": 16,
    "abbr": "CHI",
    "ast": 31,
    "blk": 8,
    "fga": 215,
    "fgm": 108,
    "fpts": "500.99",
    "fta": 40,
    "ftm": 31,
    "gp": 13,
    "min": 624,
    "pace": 224,
    "pts": 265,
    "reb": 139,
    "stl": 19,
    "team": "Chicago Bulls",
    "to": 34,
    "usg": "17.75"
  },
  {
    "3pa": 62,
    "3pm": 21,
    "abbr": "CLE",
    "ast": 53,
    "blk": 19,
    "fga": 253,
    "fgm": 113,
    "fpts": "615.63",
    "fta": 44,
    "ftm": 29,
    "gp": 15,
    "min": 720,
    "pace": 266,
    "pts": 277,
    "reb": 174,
    "stl": 21,
    "team": "Cleveland Cavaliers",
    "to": 33,
    "usg": "17.94"
  },
  {
    "3pa": 54,
    "3pm": 20,
    "abbr": "DET",
    "ast": 62,
    "blk": 13,
    "fga": 211,
    "fgm": 102,
    "fpts": "557.49",
    "fta": 42,
    "ftm": 32,
    "gp": 13,
    "min": 624,
    "pace": 229,
    "pts": 259,
    "reb": 137,
    "stl": 20,
    "team": "Detroit Pistons",
    "to": 28,
    "usg": "17.82"
  },
  {
    "3pa": 72,
    "3pm": 20,
    "abbr": "IND",
    "ast": 24,
    "blk": 13,
    "fga": 220,
    "fgm": 106,
    "fpts": "492.77",
    "fta": 38,
    "ftm": 30,
    "gp": 12,
    "min": 576,
    "pace": 226,
    "pts": 263,
    "reb": 129,
    "stl": 19,
    "team": "Indiana Pacers",
    "to": 28,
    "usg": "18.93"
  },
  {
    "3pa": 45,
    "3pm": 20,
    "abbr": "MIL",
    "ast": 31,
    "blk": 15,
    "fga": 194,
    "fgm": 97,
    "fpts": "506.57",
    "fta": 46,
    "ftm": 30,
    "gp": 13,
    "min": 624,
    "pace": 187,
    "pts": 244,
    "reb": 149,
    "stl": 15,
    "team": "Milwaukee Bucks",
    "to": 26,
    "usg": "16.06"
  },
  {
    "3pa": 54,
    "3pm": 18,
    "abbr": "ATL",
    "ast": 42,
    "blk": 17,
    "fga": 221,
    "fgm": 110,
    "fpts": "581.77",
    "fta": 38,
    "ftm": 32,
    "gp": 13,
    "min": 624,
    "pace": 234,
    "pts": 272,
    "reb": 177,
    "stl": 21,
    "team": "Atlanta Hawks",
    "to": 44,
    "usg": "18.95"
  },
  {
    "3pa": 65,
    "3pm": 26,
    "abbr": "CHA",
    "ast": 37,
    "blk": 22,
    "fga": 196,
    "fgm": 86,
    "fpts": "497.65",
    "fta": 40,
    "ftm": 32,
    "gp": 12,
    "min": 576,
    "pace": 192,
    "pts": 231,
    "reb": 129,
    "stl": 14,
    "team": "Charlotte Hornets",
    "to": 19,
    "usg": "17.00"
  },
  {
    "3pa": 53,
    "3pm": 21,
    "abbr": "MIA",
    "ast": 48,
    "blk": 18,
    "fga": 214,
    "fgm": 108,
    "fpts": "597.99",
    "fta": 62,
    "ftm": 47,
    "gp": 14,
    "min": 672,
    "pace": 222,
    "pts": 286,
    "reb": 166,
    "stl": 15,
    "team": "Miami Heat",
    "to": 29,
    "usg": "17.03"
  },
  {
    "3pa": 57,
    "3pm": 25,
    "abbr": "ORL",
    "ast": 32,
    "blk": 25,
    "fga": 198,
    "fgm": 92,
    "fpts": "537.91",
    "fta": 44,
    "ftm": 29,
    "gp": 13,
    "min": 624,
    "pace": 225,
    "pts": 240,
    "reb": 150,
    "stl": 28,
    "team": "Orlando Magic",
    "to": 39,
    "usg": "17.11"
  },
  {
    "3pa": 58,
    "3pm": 20,
    "abbr": "WAS",
    "ast": 39,
    "blk": 13,
    "fga": 232,
    "fgm": 112,
    "fpts": "583.46",
    "fta": 59,
    "ftm": 45,
    "gp": 13,
    "min": 624,
    "pace": 254.5,
    "pts": 291,
    "reb": 159,
    "stl": 24,
    "team": "Washington Wizards",
    "to": 36,
    "usg": "19.67"
  },
  {
    "3pa": 45,
    "3pm": 18,
    "abbr": "DAL",
    "ast": 37,
    "blk": 16,
    "fga": 167,
    "fgm": 92,
    "fpts": "537.84",
    "fta": 95,
    "ftm": 73,
    "gp": 13,
    "min": 624,
    "pace": 223.5,
    "pts": 276,
    "reb": 152,
    "stl": 15,
    "team": "Dallas Mavericks",
    "to": 42,
    "usg": "16.86"
  },
  {
    "3pa": 64,
    "3pm": 23,
    "abbr": "HOU",
    "ast": 45,
    "blk": 14,
    "fga": 253,
    "fgm": 130,
    "fpts": "632.31",
    "fta": 61,
    "ftm": 45,
    "gp": 13,
    "min": 624,
    "pace": 276.5,
    "pts": 330,
    "reb": 175,
    "stl": 16,
    "team": "Houston Rockets",
    "to": 39,
    "usg": "21.39"
  },
  {
    "3pa": 73,
    "3pm": 29,
    "abbr": "MEM",
    "ast": 46,
    "blk": 14,
    "fga": 208,
    "fgm": 101,
    "fpts": "551.18",
    "fta": 82,
    "ftm": 62,
    "gp": 14,
    "min": 672,
    "pace": 246,
    "pts": 294,
    "reb": 132,
    "stl": 12,
    "team": "Memphis Grizzlies",
    "to": 26,
    "usg": "16.98"
  },
  {
    "3pa": 60,
    "3pm": 19,
    "abbr": "NOP",
    "ast": 44,
    "blk": 18,
    "fga": 199,
    "fgm": 81,
    "fpts": "522.31",
    "fta": 45,
    "ftm": 30,
    "gp": 12,
    "min": 576,
    "pace": 207.5,
    "pts": 212,
    "reb": 168,
    "stl": 15,
    "team": "New Orleans Pelicans",
    "to": 26,
    "usg": "18.01"
  },
  {
    "3pa": 41,
    "3pm": 15,
    "abbr": "SAS",
    "ast": 46,
    "blk": 15,
    "fga": 202,
    "fgm": 100,
    "fpts": "518.79",
    "fta": 73,
    "ftm": 52,
    "gp": 13,
    "min": 624,
    "pace": 231.5,
    "pts": 269,
    "reb": 117,
    "stl": 16,
    "team": "San Antonio Spurs",
    "to": 27,
    "usg": "17.71"
  },
  {
    "3pa": 59,
    "3pm": 25,
    "abbr": "DEN",
    "ast": 53,
    "blk": 21,
    "fga": 194,
    "fgm": 97,
    "fpts": "539.09",
    "fta": 64,
    "ftm": 51,
    "gp": 12,
    "min": 576,
    "pace": 209,
    "pts": 271,
    "reb": 128,
    "stl": 4,
    "team": "Denver Nuggets",
    "to": 19,
    "usg": "17.96"
  },
  {
    "3pa": 113,
    "3pm": 42,
    "abbr": "MIN",
    "ast": 45,
    "blk": 8,
    "fga": 265,
    "fgm": 119,
    "fpts": "605.71",
    "fta": 72,
    "ftm": 52,
    "gp": 15,
    "min": 720,
    "pace": 296,
    "pts": 334,
    "reb": 140,
    "stl": 23,
    "team": "Minnesota Timberwolves",
    "to": 28,
    "usg": "18.86"
  },
  {
    "3pa": 49,
    "3pm": 17,
    "abbr": "POR",
    "ast": 44,
    "blk": 12,
    "fga": 185,
    "fgm": 74,
    "fpts": "510.00",
    "fta": 63,
    "ftm": 49,
    "gp": 13,
    "min": 624,
    "pace": 194.5,
    "pts": 214,
    "reb": 170,
    "stl": 16,
    "team": "Portland Trail Blazers",
    "to": 30,
    "usg": "16.49"
  },
  {
    "3pa": 63,
    "3pm": 24,
    "abbr": "OKC",
    "ast": 30,
    "blk": 18,
    "fga": 288,
    "fgm": 149,
    "fpts": "685.83",
    "fta": 60,
    "ftm": 46,
    "gp": 15,
    "min": 720,
    "pace": 309,
    "pts": 369,
    "reb": 195,
    "stl": 19,
    "team": "Oklahoma City Thunder",
    "to": 41,
    "usg": "20.29"
  },
  {
    "3pa": 58,
    "3pm": 16,
    "abbr": "UTA",
    "ast": 25,
    "blk": 19,
    "fga": 219,
    "fgm": 91,
    "fpts": "515.62",
    "fta": 48,
    "ftm": 37,
    "gp": 14,
    "min": 672,
    "pace": 223,
    "pts": 236,
    "reb": 174,
    "stl": 11,
    "team": "Utah Jazz",
    "to": 31,
    "usg": "16.63"
  },
  {
    "3pa": 45,
    "3pm": 15,
    "abbr": "GSW",
    "ast": 36,
    "blk": 6,
    "fga": 184,
    "fgm": 81,
    "fpts": "469.77",
    "fta": 59,
    "ftm": 42,
    "gp": 12,
    "min": 576,
    "pace": 204.5,
    "pts": 220,
    "reb": 136,
    "stl": 23,
    "team": "Golden State Warriors",
    "to": 28,
    "usg": "17.35"
  },
  {
    "3pa": 52,
    "3pm": 15,
    "abbr": "LAC",
    "ast": 45,
    "blk": 16,
    "fga": 265,
    "fgm": 127,
    "fpts": "651.27",
    "fta": 81,
    "ftm": 60,
    "gp": 14,
    "min": 672,
    "pace": 282.5,
    "pts": 330,
    "reb": 163,
    "stl": 25,
    "team": "Los Angeles Clippers",
    "to": 28,
    "usg": "20.45"
  },
  {
    "3pa": 49,
    "3pm": 17,
    "abbr": "LAL",
    "ast": 42,
    "blk": 21,
    "fga": 227,
    "fgm": 117,
    "fpts": "652.65",
    "fta": 77,
    "ftm": 55,
    "gp": 14,
    "min": 672,
    "pace": 238.5,
    "pts": 308,
    "reb": 190,
    "stl": 18,
    "team": "Los Angeles Lakers",
    "to": 28,
    "usg": "18.02"
  },
  {
    "3pa": 64,
    "3pm": 23,
    "abbr": "PHO",
    "ast": 34,
    "blk": 22,
    "fga": 225,
    "fgm": 119,
    "fpts": "580.21",
    "fta": 64,
    "ftm": 51,
    "gp": 13,
    "min": 624,
    "pace": 246,
    "pts": 314,
    "reb": 147,
    "stl": 14,
    "team": "Phoenix Suns",
    "to": 37,
    "usg": "19.32"
  },
  {
    "3pa": 57,
    "3pm": 18,
    "abbr": "SAC",
    "ast": 44,
    "blk": 13,
    "fga": 202,
    "fgm": 95,
    "fpts": "552.17",
    "fta": 47,
    "ftm": 34,
    "gp": 13,
    "min": 624,
    "pace": 207.5,
    "pts": 243,
    "reb": 159,
    "stl": 25,
    "team": "Sacramento Kings",
    "to": 27,
    "usg": "16.94"
  }
]